[
	{
		"id": 1,
		"name": "[간단 자취요리] 비주얼 끝장판!! 참치 스테이크 만들기 ",
		"img": "https://recipe1.ezmember.co.kr/cache/recipe/2017/04/14/8044c7b3de1b62dfdb50c68f37262be31.jpg",
		"summary": "안녕하세요 여러분?? 히히 오늘은 참치 스테이크를 만들어 봅시다!!소스는 간단하게 시판용 돈가스 소스를 사용했고, 옆의 장식은....얌싸때 먹고 냉장고에 방치해둔 셀러리를 장식으로나마 살려봤어요 :D그리고 오늘 비지엠이 조금 특별하죠..?개인적으로 딱딱 맞아 떨어지는 느낌이 너무 좋아서, 모차르트를 좋아하는데 (1도 안어울리지만 클래식 전공이었던 얌무) 유튜브 무료음원에 딱 2곡 있더라구요..ㅋㅋㅋ 언젠간 쓰겠지 하고 받아뒀는데 이때 아니면 못쓸 것 같아서 넣어봤어요![모차르트 - 세레나데 13번 G장조 \"아이네 클라이네 나흐트무지크\"]이곡은 굉장히 유명한 곡이라 많이들 아실 것 같네요!감각있으신 분들은 이미 느끼셨겠지만칼질할때 일정부분들의 박자를 편집으로 맞춰봤습니닼ㅋㅋㅋ(헛짓 매니아)",
		"info": {
			"info1": "1인분",
			"info2": "30분 이내",
			"info3": "아무나"
		},
		"ingre": [
			{
				"ingre_name": "참치캔1개(기본사이즈)",
				"ingre_count": "1개(기본사이즈)",
				"ingre_unit": "개(기본사이즈)"
			},
			{
				"ingre_name": "부침가루",
				"ingre_count": "",
				"ingre_unit": ""
			},
			{
				"ingre_name": "양파",
				"ingre_count": "1/2",
				"ingre_unit": "개"
			},
			{
				"ingre_name": "당근",
				"ingre_count": "",
				"ingre_unit": ""
			},
			{
				"ingre_name": "소금",
				"ingre_count": "2/3",
				"ingre_unit": "t"
			}
		],
		"recipe": [
			{
				"txt": "재료를 준비한다.",
				"img": "https://recipe1.ezmember.co.kr/cache/recipe/2017/04/14/19a5d39519beb1c5c2c9f16cff3d56091.png"
			},
			{
				"txt": "우선 양파를 잘게 다져준다.",
				"img": "https://recipe1.ezmember.co.kr/cache/recipe/2017/04/14/b594060fb4806c06355d7895828fc7631.png"
			},
			{
				"txt": "당근도 잘게 다져준다.",
				"img": "https://recipe1.ezmember.co.kr/cache/recipe/2017/04/14/27026d4cbaaca0375c2f3d8fcc0d61c01.png"
			},
			{
				"txt": "기름 뺀 참치와 계란, 다진 야채, 소금을 넣어 섞어준다.# 당근은 생략하셔도 되지만 이럴때라도 당근을 모르는척 먹어보세요..히히 건강에 좋습니다!!",
				"img": "https://recipe1.ezmember.co.kr/cache/recipe/2017/04/14/9cb568bbdcdfc3825d512d311c838d2b1.png"
			},
			{
				"txt": "부침가루를 넣어가며 되직하게 만들어준다.* 예상질문 : 부침가루 없으면 어떡해요? * 미리답변 : 어차피 여기서 부침가루는 반죽을 서로 붙여주기 위한 용도이니 밀가루도 좋고 튀김가루도 좋아요ㅎㅎ",
				"img": "https://recipe1.ezmember.co.kr/cache/recipe/2017/04/14/3ea267e62bc4f2810d1b40c7c6c47d121.png"
			},
			{
				"txt": "한 덩어리씩 잡고 손으로 쳐준 후 모양을 잡아준다.이 작업을 꼼꼼하게 해주셔야 구울 때 갈라지지 않아요. ",
				"img": "https://recipe1.ezmember.co.kr/cache/recipe/2017/04/14/e34cf0ec735539befaaf723a504bef3a1.png"
			},
			{
				"txt": "팬에 기름을 두르고 구워준다.중약불 ",
				"img": "https://recipe1.ezmember.co.kr/cache/recipe/2017/04/14/df5d802c91404c7b2f420cd7c8b817201.png"
			},
			{
				"txt": "한 면이 단단하게 익은 후 뒤집어준다.# 구울때 한면이 단단하게 익은 뒤에 뒤집어주셔야 모양을 유지합니다. 덜익었을때 뒤집으면 갈라져요!",
				"img": "https://recipe1.ezmember.co.kr/cache/recipe/2017/04/14/9b7d17d6e58392593ead5298c6ce7a7e1.png"
			},
			{
				"txt": "시판 돈가스 소스와 함께 곁들인다.",
				"img": "https://recipe1.ezmember.co.kr/cache/recipe/2017/04/14/8dbbf6a91f62bb2c883f11602354a8c61.png"
			}
		]
	},
	{
		"id": 2,
		"name": "[간단 자취요리] 손님 초대용! 저렴하지만 멋지게 한 상 차려보자! / 서가앤쿡 목살 스테이크 만들기",
		"img": "https://recipe1.ezmember.co.kr/cache/recipe/2016/11/18/38daef34c714b37333c0f13af2d2eb781.jpg",
		"summary": "안녕하세요 여러분들!!오늘은 주말과 잘 어울리는 특별한 요리를 준비했어용서가앤쿡 목살 스테이크를 만들어봤는데요~이거 진짜 엄청 맛있으니까 특별한날 가족과, 친구와 꼭 한번 맛있게 만들어서 드셔보세요!!음식은 비주얼이 중요해요 아무리 맛있어도 맛 없어보이면..ㅠㅠ가니쉬 여러가지 할 필요 없어요 알록달록 풀로 비주얼 업!역시 얌무스럽죠.........?",
		"info": {
			"info1": "1인분",
			"info2": "60분 이내",
			"info3": "아무나"
		},
		"ingre": [
			{
				"ingre_name": "목살",
				"ingre_count": "400",
				"ingre_unit": "g"
			},
			{
				"ingre_name": "계란",
				"ingre_count": "1",
				"ingre_unit": "개"
			},
			{
				"ingre_name": "버터",
				"ingre_count": "2",
				"ingre_unit": "T"
			},
			{
				"ingre_name": "돈가스소스",
				"ingre_count": "3",
				"ingre_unit": "T"
			},
			{
				"ingre_name": "맛술",
				"ingre_count": "2",
				"ingre_unit": "T"
			},
			{
				"ingre_name": "설탕",
				"ingre_count": "2",
				"ingre_unit": "T"
			},
			{
				"ingre_name": "굴소스",
				"ingre_count": "2",
				"ingre_unit": "T"
			},
			{
				"ingre_name": "물",
				"ingre_count": "100",
				"ingre_unit": "g"
			}
		],
		"recipe": [
			{
				"txt": "재료를 준비합니다.돼지목살, 먹을 수 있는 풀(종류 무관), 버터, 설탕, 맛술, 굴소스, 돈가스소스",
				"img": "https://recipe1.ezmember.co.kr/cache/recipe/2016/11/18/2a9a5acd846cbe95485f500c94c131a11.jpg"
			},
			{
				"txt": "먼저 소스를 만들어줍시다.소스 재료 : 돈가스소스 3T, 맛술 2T, 설탕 2T, 굴소스 2T, 물 100g",
				"img": "https://recipe1.ezmember.co.kr/cache/recipe/2016/11/18/8996f1ed4b28125ad396cb7bf68479d21.jpg"
			},
			{
				"txt": "이제 고기를 칼등으로 두드려주세요! (연육)",
				"img": "https://recipe1.ezmember.co.kr/cache/recipe/2016/11/18/16d405d8830fbe61706302beade6e8f91.jpg"
			},
			{
				"txt": "소금, 후추를 뿌려줍니다. 모두 뒤집어서 뒷면도 똑같이 밑간해주세요.",
				"img": "https://recipe1.ezmember.co.kr/cache/recipe/2016/11/18/c81e43e9749cf0145f678cf789fff0c41.jpg"
			},
			{
				"txt": "팬에 연기가 올라올 때 고기를 넣어줍니다.강불",
				"img": "https://recipe1.ezmember.co.kr/cache/recipe/2016/11/18/a0978fcca04e5032988d84efcb81e6ac1.jpg"
			},
			{
				"txt": "핏물이 송글송글 올라오면 뒤집어줍니다.강불",
				"img": "https://recipe1.ezmember.co.kr/cache/recipe/2016/11/18/272021e6ed459b25144bbba441f947251.jpg"
			},
			{
				"txt": "뒷면이 어느 정도 익으면, 불을 낮추고 버터를 넣어주세요. 앞뒷면 모두 버터에 한 번 구워줍니다.중약불",
				"img": "https://recipe1.ezmember.co.kr/cache/recipe/2016/11/18/b99475030b014bcb9df5a227897f7a7a1.jpg"
			},
			{
				"txt": "이제 준비해둔 소스를 넣고 보글보글 조려줍니다.물기가 많을 땐 중불, 거의 졸아갈 땐 약불",
				"img": "https://recipe1.ezmember.co.kr/cache/recipe/2016/11/18/9f99b4170d63a4cfaf9919cb622a5bb51.jpg"
			},
			{
				"txt": "이 정도까지 조려주시면 끝.",
				"img": "https://recipe1.ezmember.co.kr/cache/recipe/2016/11/18/e4d0e223b170cf29205a9087caa2d8441.jpg"
			},
			{
				"txt": "예쁘게 셋팅을 해봅시다. 계란후라이로 마무리.풀은 비주얼을 위해 꼭 있는 게 좋아요.(종류 무관) ",
				"img": "https://recipe1.ezmember.co.kr/cache/recipe/2016/11/18/74be733153cce8e8ee1c194105b8df431.jpg"
			}
		]
	},
	{
		"id": 3,
		"name": "[간단 자취요리] 두부를 쫄깃한 고기식감으로 만들기! 두부탕수 만들기",
		"img": "https://recipe1.ezmember.co.kr/cache/recipe/2017/11/14/ad85ee77d35f69c4420f32565f11ecd71.jpg",
		"summary": "안녕하세요 얌배추들!!오늘은 두부탕수입니다 :D 동두부가 한창 유행했을 때, 저도 많이 만들어 먹었는데 보통은 조림이나 찌개에 이용했어요. 그러다가 문득... 두부탕수를 동두부로 만들어 보면 괜찮겠다 생각이 들어 만들어 봤는데 역시 그냥 두부로 만들 때보다 훨씬 더 식감이 좋더라구요ㅎㅎ",
		"info": {
			"info1": "1인분",
			"info2": "15분 이내",
			"info3": "아무나"
		},
		"ingre": [
			{
				"ingre_name": "두부(부침용)",
				"ingre_count": "1",
				"ingre_unit": "모"
			},
			{
				"ingre_name": "각종채소",
				"ingre_count": "",
				"ingre_unit": ""
			},
			{
				"ingre_name": "물",
				"ingre_count": "300",
				"ingre_unit": "ml"
			},
			{
				"ingre_name": "식초",
				"ingre_count": "4",
				"ingre_unit": "T"
			},
			{
				"ingre_name": "간장",
				"ingre_count": "3",
				"ingre_unit": "T"
			},
			{
				"ingre_name": "설탕",
				"ingre_count": "5",
				"ingre_unit": "T"
			},
			{
				"ingre_name": "굴소스",
				"ingre_count": "1",
				"ingre_unit": "T"
			},
			{
				"ingre_name": "전분",
				"ingre_count": "",
				"ingre_unit": ""
			},
			{
				"ingre_name": "물",
				"ingre_count": "",
				"ingre_unit": ""
			}
		],
		"recipe": [
			{
				"txt": "먼저 두부를 포장 그대로 냉동실에 얼려줍니다.(하루)",
				"img": "https://recipe1.ezmember.co.kr/cache/recipe/2017/11/14/1b63219b29e0420e9981fe14a29a39871.png"
			},
			{
				"txt": "그리고 찬물에 담아 해동해서 준비합니다.얼린 두부는 꾹꾹 눌러도 안 부서져요! ",
				"img": "https://recipe1.ezmember.co.kr/cache/recipe/2017/11/14/6550584837f5ce49b0994c25eacc05cb1.png"
			},
			{
				"txt": "키친타올을 덮고 접시나 손으로 눌러 물을 짜주세요!",
				"img": "https://recipe1.ezmember.co.kr/cache/recipe/2017/11/14/ea9aea3e5aced1f1f95731a466a45e101.png"
			},
			{
				"txt": "탕수육 고기 크기로 두부를 잘라줍니다.",
				"img": "https://recipe1.ezmember.co.kr/cache/recipe/2017/11/14/9302f5cb6773c1da9187ae50331e96611.png"
			},
			{
				"txt": "비닐팩에 전분가루와 두부를 넣고 흔들어요!",
				"img": "https://recipe1.ezmember.co.kr/cache/recipe/2017/11/14/a9f8c90f408f22e23a0eceda9d5c922d1.png"
			},
			{
				"txt": "기름에 튀겨줍니다.중불",
				"img": "https://recipe1.ezmember.co.kr/cache/recipe/2017/11/14/7c63869e67e303f126eff1ba38d989eb1.png"
			},
			{
				"txt": "팬에 물과 양념들을 넣어줍니다.물 300ml(종이컵 1컵반 정도), 식초 4T, 간장 3T, 설탕 5T, 굴소스 1T",
				"img": "https://recipe1.ezmember.co.kr/cache/recipe/2017/11/14/661e9e4e88b8654250987ebd31da7e941.png"
			},
			{
				"txt": "끓으면 야채도 취향껏 넣어주세요.",
				"img": "https://recipe1.ezmember.co.kr/cache/recipe/2017/11/14/65660d6a00c9b0c74f231e66657ca7e21.png"
			},
			{
				"txt": "또 끓으면 전분물을 조금씩 넣어가며 농도를 맞춰주세요! 전분물은 물과 전분가루를 1:1로 섞으면 됩니다.",
				"img": "https://recipe1.ezmember.co.kr/cache/recipe/2017/11/14/d30409b84a47ac6ab124cc876a15f89f1.png"
			}
		]
	},
	{
		"id": 4,
		"name": "[간단 자취요리] 닭가슴살캔으로 치즈 불닭 만들기 / 혼술안주",
		"img": "https://recipe1.ezmember.co.kr/cache/recipe/2017/01/11/a593822ae8e7e1b1268cccf473202a2e1.jpg",
		"summary": "오늘은 치즈불닭 만들기를 준비해봤어요 :)간편하게 닭가슴살캔으로 만드는 방법을 준비했는데요생닭(가슴살/다리살)으로 만드셔도 좋습니다 !하지만 저녁에 집에와서 간단하게 한잔하고 싶을때나근처에 편의점 밖에 없을때 좋은 방법이겠죠?",
		"info": {
			"info1": "1인분",
			"info2": "30분 이내",
			"info3": "아무나"
		},
		"ingre": [
			{
				"ingre_name": "닭가슴살통조림(중간크기)",
				"ingre_count": "1",
				"ingre_unit": "캔"
			},
			{
				"ingre_name": "양파(작은거)",
				"ingre_count": "1",
				"ingre_unit": "개"
			},
			{
				"ingre_name": "양배추",
				"ingre_count": "1",
				"ingre_unit": "줌"
			},
			{
				"ingre_name": "고추장",
				"ingre_count": "2",
				"ingre_unit": "T"
			},
			{
				"ingre_name": "고춧가루",
				"ingre_count": "3",
				"ingre_unit": "T"
			},
			{
				"ingre_name": "간장",
				"ingre_count": "1",
				"ingre_unit": "T"
			},
			{
				"ingre_name": "설탕",
				"ingre_count": "2",
				"ingre_unit": "T"
			},
			{
				"ingre_name": "다진마늘",
				"ingre_count": "1",
				"ingre_unit": "T"
			}
		],
		"recipe": [
			{
				"txt": "재료를 준비해주세요.",
				"img": "https://recipe1.ezmember.co.kr/cache/recipe/2017/01/11/679fee7a2601907c563b059f71328d041.png"
			},
			{
				"txt": "우선 양파를 한입 크기로 썰어줍니다 :) 취향껏 채썰어도 좋아요",
				"img": "https://recipe1.ezmember.co.kr/cache/recipe/2017/01/11/69fe892b30e9a7292d17267e3bfef1b51.png"
			},
			{
				"txt": "양배추도 같은 크기로 썰어주세요",
				"img": "https://recipe1.ezmember.co.kr/cache/recipe/2017/01/11/fa3967c213cfd5c9c6c1aa3c2a215e641.png"
			},
			{
				"txt": "모든 양념을 넣고 섞어주세요고추장2T, 고춧가루3T, 간장1T, 설탕2T, 다진마늘1T",
				"img": "https://recipe1.ezmember.co.kr/cache/recipe/2017/01/11/a548486f8a6c7b658604cb206bd2dcd91.png"
			},
			{
				"txt": "팬에 닭가슴살, 야채, 양념을 모두 넣어주세요",
				"img": "https://recipe1.ezmember.co.kr/cache/recipe/2017/01/11/6949461be8eb3af760501367778f14bb1.png"
			},
			{
				"txt": "볶다보면 야채에서 물이 나오지만 물을 조금 첨가해 주셔도 좋아요.중불",
				"img": "https://recipe1.ezmember.co.kr/cache/recipe/2017/01/11/1df9478794c86682964f04060686f8071.png"
			},
			{
				"txt": "이제 기름을 두르고 센불에 마무리로 볶아주세요센불",
				"img": "https://recipe1.ezmember.co.kr/cache/recipe/2017/01/11/93b30e16864cbd0aaada030fe7fca8141.png"
			},
			{
				"txt": "이대로 먹어도 좋지만 저는 치즈를 추가해볼게요.",
				"img": "https://recipe1.ezmember.co.kr/cache/recipe/2017/01/11/38dcb91b45c3ec8c9c5f37e18722fc531.png"
			},
			{
				"txt": "전자레인지에 돌려주면 끝!전자레인지",
				"img": "https://recipe1.ezmember.co.kr/cache/recipe/2017/01/11/82d41d8668b37bac85cee8bd76112ce11.png"
			}
		]
	},
	{
		"id": 5,
		"name": "[간단 자취요리] 미친 매운맛! 빨간오뎅 집에서 만들어 먹기! / Spicy fish cakes",
		"img": "https://recipe1.ezmember.co.kr/cache/recipe/2016/11/08/4b55327585e2e041530f515f8862352e1.jpg",
		"summary": "안녕하세요 여러분~오늘은 빨간오뎅을 만들어 봤어요! 빨간 어묵이 맞지만상호명이기에 '빨간오뎅'이라고 표기할게요!술안주로도 간식, 반찬으로도 너무 맛있는 음식입니다",
		"info": {
			"info1": "4인분",
			"info2": "30분 이내",
			"info3": "아무나"
		},
		"ingre": [
			{
				"ingre_name": "어묵",
				"ingre_count": "8",
				"ingre_unit": "장"
			},
			{
				"ingre_name": "물200ml(약종이컵4/5컵)",
				"ingre_count": "200ml(약 종이컵4/5컵)",
				"ingre_unit": "ml(약 종이컵컵)"
			},
			{
				"ingre_name": "고추",
				"ingre_count": "2",
				"ingre_unit": "개"
			},
			{
				"ingre_name": "고추장",
				"ingre_count": "5",
				"ingre_unit": "T"
			},
			{
				"ingre_name": "간장",
				"ingre_count": "2",
				"ingre_unit": "T"
			},
			{
				"ingre_name": "설탕",
				"ingre_count": "4",
				"ingre_unit": "T"
			},
			{
				"ingre_name": "다진마늘",
				"ingre_count": "1",
				"ingre_unit": "T"
			}
		],
		"recipe": [
			{
				"txt": "재료를 준비합니다.어묵, 물, 고추, 고추장, 간장, 설탕, 다진마늘",
				"img": "https://recipe1.ezmember.co.kr/cache/recipe/2016/11/08/a5df154fd40ef66a77a7c8dfa55d38481.jpg"
			},
			{
				"txt": "고추 1개는 썰고, 1개는 다져줍니다. 다질 것은 씨를 제거해줍니다.",
				"img": "https://recipe1.ezmember.co.kr/cache/recipe/2016/11/08/09d33c4db68ef9b6b92307b1c94acac51.jpg"
			},
			{
				"txt": "나머지 하나는 어슷 썰어주세요.",
				"img": "https://recipe1.ezmember.co.kr/cache/recipe/2016/11/08/be6bd61260635c8db14ba861aee0f7ce1.jpg"
			},
			{
				"txt": "이제 꼬치에 어묵을 끼워줍니다. 저는 한 꼬치에 어묵을 2개씩 끼웠어요!",
				"img": "https://recipe1.ezmember.co.kr/cache/recipe/2016/11/08/cb8f898fde11d2f3f98388874e5e32d71.jpg"
			},
			{
				"txt": "팬에 물과 양념들을 넣어줍니다.양념 재료 : 물, 고추장, 간장, 설탕, 다진마늘",
				"img": "https://recipe1.ezmember.co.kr/cache/recipe/2016/11/08/b31949581a7fcea8576ab55863535cd11.jpg"
			},
			{
				"txt": "꼬치에 끼운 어묵을 넣어줍니다.고루 뒤집어가며 조려줍니다.",
				"img": "https://recipe1.ezmember.co.kr/cache/recipe/2016/11/08/a46abd6f68a8f2de64a19c780aa036321.jpg"
			},
			{
				"txt": "어슷 썬 고추도 넣고 마저 조려주세요.",
				"img": "https://recipe1.ezmember.co.kr/cache/recipe/2016/11/08/e2946f504df58034702d1d1c9849ef171.jpg"
			},
			{
				"txt": "마무리로 다진 고추를 얹어주면 끝!",
				"img": "https://recipe1.ezmember.co.kr/cache/recipe/2016/11/08/7bfaef307a5ca088d0d035bcdec58bf41.jpg"
			}
		]
	},
	{
		"id": 6,
		"name": "[간단 자취요리] 요청쇄도! 맛있는 콩불, 콩나물 불고기 만들기",
		"img": "https://recipe1.ezmember.co.kr/cache/recipe/2018/01/29/20fc80367851fdbe4f4784091ed3f27e1.jpg",
		"summary": "안녕하세요 얌배추들!오늘은 그간 요청이 많았던 콩나물 불고기, 콩불을 만들어 봤습니다.지인들이나 가족과 둘러앉아서 먹기도 참 좋은 요리죠? 좋아하는 쌈을 준비해서 같이 먹으면 더 맛있습니다 :D",
		"info": {
			"info1": "2인분",
			"info2": "30분 이내",
			"info3": "아무나"
		},
		"ingre": [
			{
				"ingre_name": "대패삼겹살",
				"ingre_count": "500",
				"ingre_unit": "g"
			},
			{
				"ingre_name": "대파",
				"ingre_count": "",
				"ingre_unit": "적당량"
			},
			{
				"ingre_name": "콩나물",
				"ingre_count": "2",
				"ingre_unit": "줌"
			},
			{
				"ingre_name": "고추장",
				"ingre_count": "5",
				"ingre_unit": "숟가락"
			},
			{
				"ingre_name": "고춧가루",
				"ingre_count": "4",
				"ingre_unit": "숟가락"
			},
			{
				"ingre_name": "간장",
				"ingre_count": "2",
				"ingre_unit": "숟가락"
			},
			{
				"ingre_name": "설탕",
				"ingre_count": "3",
				"ingre_unit": "숟가락"
			},
			{
				"ingre_name": "다진마늘",
				"ingre_count": "2",
				"ingre_unit": "숟가락"
			}
		],
		"recipe": [
			{
				"txt": "먼저 파를 큼직하게 썰어줍니다.",
				"img": "https://recipe1.ezmember.co.kr/cache/recipe/2018/01/29/4b9298cf300d94339cdf1b57c89cad2e1.png"
			},
			{
				"txt": "양념을 모두 넣고 섞어주세요.고추장 5숟가락, 고춧가루 4숟가락, 간장 2숟가락, 설탕 3숟가락, 다진 마늘 2숟가락 ",
				"img": "https://recipe1.ezmember.co.kr/cache/recipe/2018/01/29/0094538a1c230caadf0eed80affb47631.png"
			},
			{
				"txt": "팬에 고기, 콩나물을 넣고 볶아줍니다.중불",
				"img": "https://recipe1.ezmember.co.kr/cache/recipe/2018/01/29/d68726226f842b301a4f9b88bec616491.png"
			},
			{
				"txt": "만들어둔 양념을 넣고 잘 섞어줍니다.약불",
				"img": "https://recipe1.ezmember.co.kr/cache/recipe/2018/01/29/03e2aba05b15a095bf88b355f0fe47741.png"
			},
			{
				"txt": "콩나물에서 물이 나오면 중불로 높여 볶아주세요.중불",
				"img": "https://recipe1.ezmember.co.kr/cache/recipe/2018/01/29/ca523081197eff2d237f4da6859b63301.png"
			},
			{
				"txt": "대파를 넣고 한번 더 볶아주면 완성!",
				"img": "https://recipe1.ezmember.co.kr/cache/recipe/2018/01/29/a9c48bed130d7b025e888f97fdc19c141.png"
			}
		]
	},
	{
		"id": 7,
		"name": "[간단 황제 자취 요리] 스팸으로 떡갈비 만들기",
		"img": "https://recipe1.ezmember.co.kr/cache/recipe/2018/11/14/f4be994c5ec79594895e945d1e21e6341.jpg",
		"summary": "스팸으로 떡갈비 만들기 가능 할까요!?",
		"info": {
			"info1": "2인분",
			"info2": "30분 이내",
			"info3": "초급"
		},
		"ingre": [
			{
				"ingre_name": "스팸또는리챔1통(340g)",
				"ingre_count": "1통(340g)",
				"ingre_unit": "통(g)"
			},
			{
				"ingre_name": "달걀",
				"ingre_count": "2",
				"ingre_unit": "개"
			},
			{
				"ingre_name": "당근",
				"ingre_count": "1/4",
				"ingre_unit": ""
			},
			{
				"ingre_name": "새송이버섯",
				"ingre_count": "1",
				"ingre_unit": "개"
			},
			{
				"ingre_name": "파",
				"ingre_count": "1",
				"ingre_unit": "뿌리"
			},
			{
				"ingre_name": "마늘",
				"ingre_count": "2",
				"ingre_unit": "개"
			}
		],
		"recipe": [
			{
				"txt": "제일 먼저 파를 잘게 쫑쫑 썰어줍니다.",
				"img": "https://recipe1.ezmember.co.kr/cache/recipe/2018/11/14/607f6efdceade34bb9f1b444100b59fb1.jpg"
			},
			{
				"txt": "당근과 버섯은 작은 네모네모 큐브 모양으로 다져줍니다. 버섯종류는 취향에 따라 선택 가능합니다.버섯종류는 취향에 따라 선택 가능합니다.",
				"img": "https://recipe1.ezmember.co.kr/cache/recipe/2018/11/14/681ea6c1db4f12d6ffe3c54dec45a5641.jpg"
			},
			{
				"txt": "마늘 기름을 내기 위한 마늘은 잘게 다져줍니다.",
				"img": "https://recipe1.ezmember.co.kr/cache/recipe/2018/11/14/47c37398408dcb7111be5b86e31a05bf1.jpg"
			},
			{
				"txt": "볼에 스팸 또는 리챔을 넣고 손으로 마구 으깨줍니다. 마구마구 으깨주시면 마치 고기를 다져 놓은 듯한 모양이 됩니다.",
				"img": "https://recipe1.ezmember.co.kr/cache/recipe/2018/11/14/b66d6f8fe91175e2823aee7cbc4ed4e01.jpg"
			},
			{
				"txt": "그다음 썰어두었던 재료들을 모두 넣어주세요.",
				"img": "https://recipe1.ezmember.co.kr/cache/recipe/2018/11/14/8b7fcd11668260d17a09a098aeb0de1d1.jpg"
			},
			{
				"txt": "재료들을 넣고 잘 섞어주세요.",
				"img": "https://recipe1.ezmember.co.kr/cache/recipe/2018/11/14/815861ad76d77eea7ca3b33f1e9947f91.jpg"
			},
			{
				"txt": "계란 2개를 넣어주세요.",
				"img": "https://recipe1.ezmember.co.kr/cache/recipe/2018/11/14/7941261fd927a808209b1cfe4cfde34f1.jpg"
			},
			{
				"txt": "그 후 반죽해주세요. 잘 치대지 않으면 중간에 부서질 수 도 있으니 잘 치대주세요.",
				"img": "https://recipe1.ezmember.co.kr/cache/recipe/2018/11/14/d89ab642845f468c9f04589511e6b5591.jpg"
			},
			{
				"txt": "반죽을 적당한 크기로 만들어주세요.",
				"img": "https://recipe1.ezmember.co.kr/cache/recipe/2018/11/14/0da823f555dc447a6b89327a4368a0091.jpg"
			},
			{
				"txt": "기름을 두른 팬에 넣어 구워주세요.",
				"img": "https://recipe1.ezmember.co.kr/cache/recipe/2018/11/14/0434f027e4c6ca0824a4068c38b62cd31.jpg"
			},
			{
				"txt": "마늘을 넣어주어 마늘향을 내줍니다. 마늘은 향만 내주는 역할이기 때문에 처음에 넣어서 타는일이 없게 해주세요.마늘은 향만 내주는 역할이기 때문에 타지않게 요리조리 뒤집어주세요.",
				"img": "https://recipe1.ezmember.co.kr/cache/recipe/2018/11/14/2a56a7aa138e15b7f92f6ac5ee84ceef1.jpg"
			},
			{
				"txt": "다익은 떡갈비는 키친타올을 깐 접시에 건져서 기름을 빼주세요. 기름이 빠진 떡갈비는 그릇에 담아줍니다.",
				"img": "https://recipe1.ezmember.co.kr/cache/recipe/2018/11/14/5215c7afa6914937a412db18a7e46aed1.jpg"
			}
		]
	},
	{
		"id": 8,
		"name": "[간단 자취요리] 무도 불백깡 사건, 바로 그 요리! 돼지불백 만들기 ",
		"img": "https://recipe1.ezmember.co.kr/cache/recipe/2016/08/10/43a2f000bf2755c7105e06106c709dc91.jpg",
		"summary": "안녕하세요 여러분들~!!오늘이 수능 D-100일이라고 하네요! 수험생 분들 모두 힘힘!!!!오늘은 예전에 무한도전에서 택시기사편인가? 어디에서 나온돼지불백 불백깡사건(?)속 돼지불백을 만들어 봤습니다ㅋㅋㅋㅋ돼지불백은 돼지불고기백반의 줄임말인데요~오늘의 요리는 돼지불고기가 맞지만 부르기 쉽게 돼지불백이라고 명칭할게요 :)그 연남동 기사식당은 저도 한번 가서 먹어봤는데요그렇게 기대한 만큼은 아니지만 약간짜고 약간달고..그냥 무난하더라구요 ㅎㅎ특징이라면 야채가 안들어가고 국물없이 바싹 불고기느낌?!오늘은 그래서 초간단 버전 돼지불백을 준비했습니다",
		"info": {
			"info1": "1인분",
			"info2": "30분 이내",
			"info3": "초급"
		},
		"ingre": [
			{
				"ingre_name": "돼지고기앞다리",
				"ingre_count": "300",
				"ingre_unit": "g"
			},
			{
				"ingre_name": "다진파",
				"ingre_count": "2",
				"ingre_unit": "T"
			},
			{
				"ingre_name": "다진마늘",
				"ingre_count": "1",
				"ingre_unit": "T"
			},
			{
				"ingre_name": "간장",
				"ingre_count": "3",
				"ingre_unit": "T"
			},
			{
				"ingre_name": "설탕",
				"ingre_count": "2",
				"ingre_unit": "T"
			},
			{
				"ingre_name": "맛술",
				"ingre_count": "1",
				"ingre_unit": "T"
			},
			{
				"ingre_name": "참기름",
				"ingre_count": "2",
				"ingre_unit": "T"
			},
			{
				"ingre_name": "후추",
				"ingre_count": "",
				"ingre_unit": "약간"
			}
		],
		"recipe": [
			{
				"txt": "재료를 준비합니다. 주 재료 : 앞다리살 300g, 다진파2T, 다진마늘1T, 양념장 : 간장3T, 설탕2T, 맛술1T, 참기름2T, 후추",
				"img": "https://recipe1.ezmember.co.kr/cache/recipe/2016/08/10/f04fcea2ee291f44f766bcfdfb04d6741.png"
			},
			{
				"txt": "우선 대파를 찹찹찹 다져줍니다.",
				"img": "https://recipe1.ezmember.co.kr/cache/recipe/2016/08/10/2ef04535b41f3d0d64e92fb71d7ea5021.png"
			},
			{
				"txt": "분량의 양념장을 넣고 섞어줍니다.양념장 : 간장3T, 설탕2T, 맛술1T, 참기름2T, 후추",
				"img": "https://recipe1.ezmember.co.kr/cache/recipe/2016/08/10/4ddd556c280dca4aced3b71dd14b38ec1.png"
			},
			{
				"txt": "고기를 넣고 조물조물 무쳐줍니다. 골고루 빡빡 무쳐줘야 간이 잘 베어요! 냉장고에 숙성해뒀다가 먹으면 더 맛있어요!",
				"img": "https://recipe1.ezmember.co.kr/cache/recipe/2016/08/10/42daffdca44e4cbd445e9d470a50fc9a1.png"
			},
			{
				"txt": "기름을 조금만 두르고 볶아줍니다. 펼쳐서 굽기 -> 섞기를 반복해줍니다. 물이 생기면 없어질때까지 중불에 구워주세요!",
				"img": "https://recipe1.ezmember.co.kr/cache/recipe/2016/08/10/189478b249b499d9cc52a16e4660989b1.png"
			},
			{
				"txt": "마지막은 센불에서 휘리릭볶아 마무리하면 무한도전 돼지불백 생성완료!",
				"img": "https://recipe1.ezmember.co.kr/cache/recipe/2016/08/10/30bf511998844aea746a4c3d151b51f71.png"
			}
		]
	},
	{
		"id": 9,
		"name": "[간단 자취요리] 너무 맛있잖아...? 단짠 끝판왕! 파불고기 만들기",
		"img": "https://recipe1.ezmember.co.kr/cache/recipe/2017/08/11/d0a9ba7e19ccbaa4e4a119a0af73bb151.jpg",
		"summary": "안녕하세요 얌배추들!!오늘은 제가 진짜 좋아하는 메뉴인 파불고기입니다 :D단짠단짠 고기에 상큼한 파채가 찰떡궁합인 메뉴예요!이건 꼭 한번 만들어서 드시길 추천합니다. 정말 맛있어요!!",
		"info": {
			"info1": "1인분",
			"info2": "30분 이내",
			"info3": "초급"
		},
		"ingre": [
			{
				"ingre_name": "대패삼겹살",
				"ingre_count": "400",
				"ingre_unit": "g"
			},
			{
				"ingre_name": "대파",
				"ingre_count": "",
				"ingre_unit": "적당량"
			},
			{
				"ingre_name": "간장",
				"ingre_count": "4",
				"ingre_unit": "T"
			},
			{
				"ingre_name": "설탕",
				"ingre_count": "2",
				"ingre_unit": "T"
			},
			{
				"ingre_name": "마늘",
				"ingre_count": "1",
				"ingre_unit": "T"
			},
			{
				"ingre_name": "맛술",
				"ingre_count": "2",
				"ingre_unit": "T"
			},
			{
				"ingre_name": "참기름",
				"ingre_count": "1",
				"ingre_unit": "T"
			},
			{
				"ingre_name": "간장",
				"ingre_count": "1",
				"ingre_unit": "T"
			},
			{
				"ingre_name": "설탕",
				"ingre_count": "1/2",
				"ingre_unit": "T"
			},
			{
				"ingre_name": "식초",
				"ingre_count": "1",
				"ingre_unit": "T"
			}
		],
		"recipe": [
			{
				"txt": "먼저 대파를 채썰어줍니다.파채칼을 사용하셔도 좋아요!",
				"img": "https://recipe1.ezmember.co.kr/cache/recipe/2017/08/11/d0baaccd05f81c2c2c7535430a6e47f71.jpg"
			},
			{
				"txt": "대파는 찬물에 담가둡니다.매운맛을 제거하기 위해서요~",
				"img": "https://recipe1.ezmember.co.kr/cache/recipe/2017/08/11/6345763e5c0402e9a919886d473f61411.jpg"
			},
			{
				"txt": "대패삼겹살도 먹기 좋게 썰어주세요!",
				"img": "https://recipe1.ezmember.co.kr/cache/recipe/2017/08/11/b64c8a054932f5794f0ddc8398d16f361.jpg"
			},
			{
				"txt": "모든 고기양념을 더해서 넣고 섞어주세요.",
				"img": "https://recipe1.ezmember.co.kr/cache/recipe/2017/08/11/95d53d2816c159ca8c6a7b828331ff021.jpg"
			},
			{
				"txt": "고기를 넣고 볶아줍니다.강불대패삼겹은 뭉치기 쉬우니 잘 흔들어 풀어줘요!",
				"img": "https://recipe1.ezmember.co.kr/cache/recipe/2017/08/11/df55df5c7ff86dfd2a07c5fac903a4611.jpg"
			},
			{
				"txt": "고기가 익으면 파채 절반도 넣어서 볶아줍니다.강불",
				"img": "https://recipe1.ezmember.co.kr/cache/recipe/2017/08/11/c3fc0bc6bab95657d560d67bf5001fcd1.jpg"
			},
			{
				"txt": "파채소스를 만들어줍니다.",
				"img": "https://recipe1.ezmember.co.kr/cache/recipe/2017/08/11/0c7162325b8cae39802603fd8730a1241.jpg"
			},
			{
				"txt": "남은파채를 넣고 잘무쳐주세요.",
				"img": "https://recipe1.ezmember.co.kr/cache/recipe/2017/08/11/ed54c3fa2e69f1e8d117a81ede866b681.jpg"
			},
			{
				"txt": "고기 옆에 놓고 같이 드시면됩니다 :D",
				"img": "https://recipe1.ezmember.co.kr/cache/recipe/2017/08/11/4818dd4fcc4f937e2da43c0d34edb6b11.jpg"
			}
		]
	},
	{
		"id": 10,
		"name": "[간단 자취요리] 칼집 삼겹살? 놉!!! 칼집 소세지 야채볶음/쏘야! ",
		"img": "https://recipe1.ezmember.co.kr/cache/recipe/2016/06/30/b37b5d07d98192dc250949fa4e05d7251.jpg",
		"summary": "안녕하쎄요 여러분~~!오늘은 소세지 야채볶음 일명 쏘야를 만들어봤어요쏘야는 술안주나 밥반찬으로 최고인 메뉴죠?칼집은 어떻게 내셔도 상관없지만 오늘 저는 칼집을 촘촘하게많이 넣어서 사이사이에 양념이 더 잘 베도록 만들어봤어요야채는 기본적으로 양파외에는 있는야채 넣으시면 돼요!예를들어 파프리카가 없다면 오이고추의 씨를 빼서 넣으셔도 되고양파의 양을 늘려도 되고, 무한 응용이 가능하겠죠?",
		"info": {
			"info1": "1인분",
			"info2": "15분 이내",
			"info3": "중급"
		},
		"ingre": [
			{
				"ingre_name": "비엔나소세지",
				"ingre_count": "",
				"ingre_unit": ""
			},
			{
				"ingre_name": "양파",
				"ingre_count": "1/2",
				"ingre_unit": "개"
			},
			{
				"ingre_name": "파프리카",
				"ingre_count": "",
				"ingre_unit": ""
			},
			{
				"ingre_name": "케찹",
				"ingre_count": "5",
				"ingre_unit": "T"
			},
			{
				"ingre_name": "굴소스",
				"ingre_count": "2",
				"ingre_unit": "T"
			},
			{
				"ingre_name": "설탕",
				"ingre_count": "1",
				"ingre_unit": "T"
			}
		],
		"recipe": [
			{
				"txt": "재료를 준비합니다.비엔나소세지, 양파 1/2개, 파프리카,케찹 5T, 굴소스 2T, 설탕 1T약불에 살살 저으면서 섞어주세요",
				"img": "https://recipe1.ezmember.co.kr/cache/recipe/2016/06/30/5b3c3f0ad33c8b4928b7b0777ec1c7761.jpg"
			},
			{
				"txt": "들어갈 야채를 썰어줍니다. 비슷한 크기로 썰어주면 좋아요.양파 1/2개, 파프리카",
				"img": "https://recipe1.ezmember.co.kr/cache/recipe/2016/06/30/aa1c0554a21457f17414026f89e329711.jpg"
			},
			{
				"txt": "소세지에 칼집을 내줍니다. 칼집 모양은 마음대로 하셔도 좋아요.",
				"img": "https://recipe1.ezmember.co.kr/cache/recipe/2016/06/30/7762b6e9454d2dfab2aa964717f594631.jpg"
			},
			{
				"txt": "촘촘하게 내면 간이 더 잘 배요!",
				"img": "https://recipe1.ezmember.co.kr/cache/recipe/2016/06/30/9e566dfa79f749da489d5a0ee8a60ec31.jpg"
			},
			{
				"txt": "팬에 기름을 둘러주세요.",
				"img": "https://recipe1.ezmember.co.kr/cache/recipe/2016/06/30/626b1aacdee75f68136668245adbfb2b1.jpg"
			},
			{
				"txt": "기름에 야채부터 볶아줍니다.",
				"img": "https://recipe1.ezmember.co.kr/cache/recipe/2016/06/30/b6695c0d0d6032a41f690486ec20783e1.jpg"
			},
			{
				"txt": "소세지를 넣어주세요. 칼집이 살짝 벌어질때까지 볶아줍니다.",
				"img": "https://recipe1.ezmember.co.kr/cache/recipe/2016/06/30/1351e96194e4ae27203a0d66ad4633bc1.jpg"
			},
			{
				"txt": "분량의 양념장을 넣어줍니다.케찹 5T, 굴소스 2T, 설탕 1T",
				"img": "https://recipe1.ezmember.co.kr/cache/recipe/2016/06/30/f59abc7b2b502afae7979eb0a3cb804b1.jpg"
			},
			{
				"txt": "마지막으로 살짝만 더 볶아주세요.",
				"img": "https://recipe1.ezmember.co.kr/cache/recipe/2016/06/30/6b85614d8617333a6f57e11ad7be2c891.jpg"
			},
			{
				"txt": "윤기 좔좔~칼집 쏘야 완성!",
				"img": "https://recipe1.ezmember.co.kr/cache/recipe/2016/06/30/07ef21c5152a9d746a8dbd5683ebaad01.jpg"
			}
		]
	},
	{
		"id": 11,
		"name": "[간단 자취요리] 얌무의 술안주 요리! 두부김치 만들기 / Tofu and kimchi",
		"img": "https://recipe1.ezmember.co.kr/cache/recipe/2016/10/26/ca366e4bcd477f02c9a36d092fa816c61.jpg",
		"summary": "안녕하세요 여러분들!!!오늘은 어제 인스타로 예고했었던 얌무의 술안주! 두부김치입니다오늘 이렇게 비가오는건 몰랐는데 타이밍도 나이스하네요 ㅎㅎ이런날 두부김치에 막걸리/소주 한잔 좋죠?오늘 하룻동안도 고생 많으셨을텐데 저녁에 두부김치에 간단하게 반주하셔도 좋을 것 같네요 :)",
		"info": {
			"info1": "1인분",
			"info2": "30분 이내",
			"info3": "아무나"
		},
		"ingre": [
			{
				"ingre_name": "두부",
				"ingre_count": "1",
				"ingre_unit": "모"
			},
			{
				"ingre_name": "신김치",
				"ingre_count": "",
				"ingre_unit": "밥그릇가득"
			},
			{
				"ingre_name": "설탕",
				"ingre_count": "1",
				"ingre_unit": "T"
			},
			{
				"ingre_name": "고춧가루",
				"ingre_count": "1~1.5T",
				"ingre_unit": "~.T"
			},
			{
				"ingre_name": "참기름",
				"ingre_count": "2",
				"ingre_unit": "T"
			}
		],
		"recipe": [
			{
				"txt": "재료를 준비합니다.신김치, 고춧가루, 참기름, 설탕",
				"img": "https://recipe1.ezmember.co.kr/cache/recipe/2016/10/26/b4bb1eb9acd90d36c60ad0874e10e7de1.jpg"
			},
			{
				"txt": "우선 기름을 두르고, 김치를 볶아줍니다!",
				"img": "https://recipe1.ezmember.co.kr/cache/recipe/2016/10/26/94aa2c1f7aea161bb463d2d4031276bc1.jpg"
			},
			{
				"txt": "중간중간 물을 넣어가면서 촉촉하게 볶아줘요!",
				"img": "https://recipe1.ezmember.co.kr/cache/recipe/2016/10/26/9d5108e3949de349daeb361e1f1bc43d1.jpg"
			},
			{
				"txt": "설탕, 고춧가루도 넣어줍니다.",
				"img": "https://recipe1.ezmember.co.kr/cache/recipe/2016/10/26/fa002e7eb52bd4f98d7031c84f708a681.jpg"
			},
			{
				"txt": "불 끄기 전 참기름을 둘러주세요.",
				"img": "https://recipe1.ezmember.co.kr/cache/recipe/2016/10/26/fe412a565231cf07490ec4147985da4f1.jpg"
			},
			{
				"txt": "이제 두부를 간단하게 데치는 법 알려드릴게요! 그릇에 두부와 두부가 잠길만큼의 물을 넣은 뒤 전자렌지에 2~3분 돌려줍니다.전자레인지",
				"img": "https://recipe1.ezmember.co.kr/cache/recipe/2016/10/26/3c012151430f66699d562cd2397a08da1.jpg"
			},
			{
				"txt": "이제 먹기 좋은 크기로 썰어주시면 됩니다.뜨거우니 손 조심하세요!",
				"img": "https://recipe1.ezmember.co.kr/cache/recipe/2016/10/26/6101899e9aab5a0b8161a3f4692743341.jpg"
			},
			{
				"txt": "예쁘게 셋팅만 하면 끝!",
				"img": "https://recipe1.ezmember.co.kr/cache/recipe/2016/10/26/41f9c35ec98eb6552d74d22b844060811.jpg"
			}
		]
	},
	{
		"id": 12,
		"name": "[간단 자취요리] 닭고기 잡채 느낌! 닭당면 만들기",
		"img": "https://recipe1.ezmember.co.kr/cache/recipe/2017/08/21/9017e4835e397996dc2efe28e65279681.jpg",
		"summary": "안녕하세요 얌배추들!!오늘은 닭당면입니다.네... 닭당면이라는 메뉴는 실제로 없지만 제가 이름 지어봤어요. 너무 정직하게 닭과 당면... 닭당면 ㅋㅋㅋㅋ예전에 잡채를 간단 버전으로 올렸는데 얌배추들이 자꾸 야채 싫다고....하핫 그래서 이번 요리는 야채를 뺀 잡채 느낌이라고 생각하시면 될 것 같네요! 모양은 좀 그래보여도 맛있습니다.보통 요리하려고 당면을 사면 한두 번 사용하고 방치가 되는데요~ 그럴 때 이거 만들어서 드세요 ㅎㅎ!",
		"info": {
			"info1": "1인분",
			"info2": "10분 이내",
			"info3": "초급"
		},
		"ingre": [
			{
				"ingre_name": "당면",
				"ingre_count": "1",
				"ingre_unit": "인분"
			},
			{
				"ingre_name": "닭가슴살캔",
				"ingre_count": "1",
				"ingre_unit": "개"
			},
			{
				"ingre_name": "양파",
				"ingre_count": "1/2",
				"ingre_unit": "개"
			},
			{
				"ingre_name": "간장",
				"ingre_count": "2",
				"ingre_unit": "T"
			},
			{
				"ingre_name": "고춧가루",
				"ingre_count": "1/2~1T",
				"ingre_unit": "~T"
			},
			{
				"ingre_name": "굴소스",
				"ingre_count": "1",
				"ingre_unit": "T"
			},
			{
				"ingre_name": "설탕",
				"ingre_count": "1",
				"ingre_unit": "T"
			},
			{
				"ingre_name": "다진마늘",
				"ingre_count": "1",
				"ingre_unit": "T"
			}
		],
		"recipe": [
			{
				"txt": "먼저 양파를 얇게 채썰어주세요.",
				"img": "https://recipe1.ezmember.co.kr/cache/recipe/2017/08/21/dabecac3f6f035335d155f9a26fbeb3c1.jpg"
			},
			{
				"txt": "물을 넣고 당면부터 삶아줍니다.",
				"img": "https://recipe1.ezmember.co.kr/cache/recipe/2017/08/21/4bcf0b600a34334b1c698e1338b669361.jpg"
			},
			{
				"txt": "팬에 기름을 두르고 양파를 볶아줍니다.중불",
				"img": "https://recipe1.ezmember.co.kr/cache/recipe/2017/08/21/e3318b4c39b44968cd226e30699c591e1.jpg"
			},
			{
				"txt": "삶아둔 당면, 닭가슴살, 양념을 넣고 볶아주세요.두 화구에서 양파 뽁기/면 삶기 같이 진행하면 빨라요!",
				"img": "https://recipe1.ezmember.co.kr/cache/recipe/2017/08/21/989b1423d2139254d58091e0f4358fa81.jpg"
			}
		]
	},
	{
		"id": 13,
		"name": "[간단 자취요리] 불 없이! 전자렌지로 8분 제육볶음 만들기! ",
		"img": "https://recipe1.ezmember.co.kr/cache/recipe/2016/06/13/ddeb9442a0c1e3b59e1142267dacb3511.jpg",
		"summary": "오늘은 모두가 좋아하는 제육볶음입니다!!노 가스렌지! 불 없이! 전자렌지로 만드는 제육볶음 이에요 :D얼마전 한 구독자분께서 가스렌지가 없고 전자렌지밖에 없는고시원들도 많아서 전자렌지 요리를 추천해주셨는데요~그래서 이번요리는 가스렌지 없으신 분들도! 더워서 요리하기 귀찮으신 분들도! 볶는 작업이 귀찮으신 분들도 모두 OK!( 저 무슨 홈쇼핑에서 뭐 파는애 같네요 허허 )고기는 보통 제육에는 삼겹살,목살,전지(앞다리살)를 쓰는데요오늘은 저렴한 전지로 만들어봤습니다 :)원하시는 고기 사용하시면 돼요!*4분 먼저 돌리고 고기 저으실때 윗부분만 대충 저으면 안되고밑에있는 고기까지 완전히 뒤집히게 확실히 저어주세요!",
		"info": {
			"info1": "1인분",
			"info2": "15분 이내",
			"info3": "아무나"
		},
		"ingre": [
			{
				"ingre_name": "돼지고기",
				"ingre_count": "400",
				"ingre_unit": "g"
			},
			{
				"ingre_name": "양파",
				"ingre_count": "1",
				"ingre_unit": "개"
			},
			{
				"ingre_name": "대파",
				"ingre_count": "1",
				"ingre_unit": "줌"
			},
			{
				"ingre_name": "고춧가루",
				"ingre_count": "2",
				"ingre_unit": "T"
			},
			{
				"ingre_name": "고추장",
				"ingre_count": "2",
				"ingre_unit": "T"
			},
			{
				"ingre_name": "설탕",
				"ingre_count": "2",
				"ingre_unit": "T"
			},
			{
				"ingre_name": "간장",
				"ingre_count": "2",
				"ingre_unit": "T"
			},
			{
				"ingre_name": "다진마늘",
				"ingre_count": "1",
				"ingre_unit": "T"
			}
		],
		"recipe": [
			{
				"txt": "재료를 준비해주세요.",
				"img": "https://recipe1.ezmember.co.kr/cache/recipe/2016/06/13/ce4492934870ef054400b38fd91ff3eb1.jpg"
			},
			{
				"txt": "대파를 먹기 좋은 크기로 썰어주세요.",
				"img": "https://recipe1.ezmember.co.kr/cache/recipe/2016/06/13/355cd74b0966a8fb62f3a600ad54b0eb1.jpg"
			},
			{
				"txt": "양파도 마찬가지 입니다.",
				"img": "https://recipe1.ezmember.co.kr/cache/recipe/2016/06/13/a44e2d396c8b9d21a473f0147f3356931.jpg"
			},
			{
				"txt": "준비한 양념을 고기에 넣고 섞어주세요.",
				"img": "https://recipe1.ezmember.co.kr/cache/recipe/2016/06/13/9fe8a045d163efba679b646c2c2947831.jpg"
			},
			{
				"txt": "섞은 고기에 손질한 야채도 함께 넣어 버무려주세요.",
				"img": "https://recipe1.ezmember.co.kr/cache/recipe/2016/06/13/2cdfb5e64c6771fd6c3922764e363eaf1.jpg"
			},
			{
				"txt": "버무린 고기에 후추도 넣어주세요.",
				"img": "https://recipe1.ezmember.co.kr/cache/recipe/2016/06/13/e2f05d2da2d59694af607d42ed6558bc1.jpg"
			},
			{
				"txt": "준비 된 고기에 비닐팩을 씌운 후 전자레인지에 돌려주세요.전자레인지",
				"img": "https://recipe1.ezmember.co.kr/cache/recipe/2016/06/13/19ce577d360db1a384382c899dd1b9301.jpg"
			},
			{
				"txt": "일단 4분을 먼저 돌려줍니다.",
				"img": "https://recipe1.ezmember.co.kr/cache/recipe/2016/06/13/7e45a49f67f02e19cc53545006aefc5d1.jpg"
			},
			{
				"txt": "4분 뒤, 고기를 한 번 휘저어 줍니다.",
				"img": "https://recipe1.ezmember.co.kr/cache/recipe/2016/06/13/3836a3ad98096ed203fcab829dfcacb71.jpg"
			},
			{
				"txt": "그리고 다시 4분을 돌려줍니다.",
				"img": "https://recipe1.ezmember.co.kr/cache/recipe/2016/06/13/11e8f6a6599ce93a5b34c5a8f2b79dcf1.jpg"
			},
			{
				"txt": "고기가 다 익었으면 완성입니다.",
				"img": "https://recipe1.ezmember.co.kr/cache/recipe/2016/06/13/321501e06c40bb6f30b157b4ed3538821.jpg"
			}
		]
	},
	{
		"id": 14,
		"name": "[간단 자취요리] 이보다 더 쉬운 잡채는 없다. 자취버전 잡채 만들기",
		"img": "https://recipe1.ezmember.co.kr/cache/recipe/2017/06/02/c198ded903712ff7a4604ff4aedef5241.jpg",
		"summary": "안녕하세요 여러분 :D씬나는 금요일이 돌아왔네요ㅎㅎ오늘은 자취버전 잡채를 만들어 봤어요!최대한 생략할 수 있는 재료는 생략하고,복잡할 수 있는 과정도 생략했어요!정석 잡채는...정말 복잡합니다우선 시금치 따로 데쳐서 물기 짜서 밑간 해야되고,고기 따로 간장양념에 재워뒀다가 볶고, 야채들 색이 연한 순서대로 하나하나 따로 볶아내고볶을때마다 개별 밑간합니다.....엄청나죠?사실 그래서 잡채는 어렵다기보다는 굉장히 귀찮은 요리중 하나에요ㅋㅋㅋㅋ부모님이 잡채 해주시면 꼭 감사하다고 마음을 전하세요!!",
		"info": {
			"info1": "2인분",
			"info2": "30분 이내",
			"info3": "아무나"
		},
		"ingre": [
			{
				"ingre_name": "당면",
				"ingre_count": "2",
				"ingre_unit": "인분"
			},
			{
				"ingre_name": "오이고추",
				"ingre_count": "2",
				"ingre_unit": "개"
			},
			{
				"ingre_name": "양파1개(큰거는반개)",
				"ingre_count": "1개(큰거는 반개)",
				"ingre_unit": "개(큰거는 반개)"
			},
			{
				"ingre_name": "어묵",
				"ingre_count": "2",
				"ingre_unit": "장"
			},
			{
				"ingre_name": "간장",
				"ingre_count": "5~6T",
				"ingre_unit": "~T"
			},
			{
				"ingre_name": "설탕",
				"ingre_count": "2",
				"ingre_unit": "T"
			},
			{
				"ingre_name": "다진마늘1+1/2T",
				"ingre_count": "1+1/2",
				"ingre_unit": "T"
			}
		],
		"recipe": [
			{
				"txt": "재료를 준비한다.",
				"img": "https://recipe1.ezmember.co.kr/cache/recipe/2017/06/02/7f249137f364080d1b18955f8639199f1.png"
			},
			{
				"txt": "양파는 먹기 좋은 크기로 채썬다.",
				"img": "https://recipe1.ezmember.co.kr/cache/recipe/2017/06/02/2b58b2262eb436c1a6d726c2fad4a5e11.png"
			},
			{
				"txt": "당근도 가늘게 채썬다.",
				"img": "https://recipe1.ezmember.co.kr/cache/recipe/2017/06/02/634ffd3615e34d3afc95913e7d8e46181.png"
			},
			{
				"txt": "오이고추는 꼭지와 씨를 제거한다.",
				"img": "https://recipe1.ezmember.co.kr/cache/recipe/2017/06/02/007ffa1fa50de6c202900ab1ae8e6c521.png"
			},
			{
				"txt": "오이고추도 가늘게 채썬다.",
				"img": "https://recipe1.ezmember.co.kr/cache/recipe/2017/06/02/6f4a97d3c12df41f243ad48bd58eaf521.png"
			},
			{
				"txt": "어묵도 채썬다.",
				"img": "https://recipe1.ezmember.co.kr/cache/recipe/2017/06/02/ffadf67d1be4b1c86263cc7a6c684ee81.png"
			},
			{
				"txt": "물에 불린 당면을 3분 정도 삶아준다.",
				"img": "https://recipe1.ezmember.co.kr/cache/recipe/2017/06/02/a90eb06c18b620d1d1a94c8ce27603211.png"
			},
			{
				"txt": "삶은 후 체에 건진다.",
				"img": "https://recipe1.ezmember.co.kr/cache/recipe/2017/06/02/4d2a76e01e3577b80e1fcf75ab14c50b1.png"
			},
			{
				"txt": "팬에 기름을 두르고 양파와 당근을 볶는다.",
				"img": "https://recipe1.ezmember.co.kr/cache/recipe/2017/06/02/8702e948d60e4a13e676228128d6e8831.png"
			},
			{
				"txt": "양파가 살짝 익으면 어묵도 넣어서 볶는다.",
				"img": "https://recipe1.ezmember.co.kr/cache/recipe/2017/06/02/7f743fa180f29f3e11219cf18d87b3a31.png"
			},
			{
				"txt": "삶아둔 당면과 양념을 넣는다.",
				"img": "https://recipe1.ezmember.co.kr/cache/recipe/2017/06/02/939d1586d1f25028f4541975156c515d1.png"
			},
			{
				"txt": "참기름을 두르고 고추채를 넣고 섞어 마무리!",
				"img": "https://recipe1.ezmember.co.kr/cache/recipe/2017/06/02/42ab313ae552a390cbe7c0c8ddee253e1.png"
			}
		]
	},
	{
		"id": 15,
		"name": "[간단 자취요리] 자취버전 너겟 탕수육 만들기 / 탕수육 소스",
		"img": "https://recipe1.ezmember.co.kr/cache/recipe/2017/03/24/51e7f407a1a54f9940a3d6cadd57f3d61.jpg",
		"summary": "안녕하세요 여러분들~오늘은 모두가 좋아하는 탕수육입니다!너겟을 사용해서 간단하고 만두를 이용한 탕수만두,돈가스를 사용해서 탕수 돈가스 등등~무한 응용이 가능하다는 점이 좋죠 :)저는 찍먹파이지만 영상을 위해서 부먹으로.......또륵그래도 엄청 맛있게 먹었습니닷제가 예전에 올린 레시피 중에 돼지고기를 튀겨서 만들고소스는 간단하게 오렌지 주스를 사용해서 만든 영상도 있는데요~돼지고기를 튀기고싶으신 분들이나, 오렌지주스 향이 솔솔 나는새콤한 소스도 만들어보고싶다 하시면 한번 보세용~",
		"info": {
			"info1": "2인분",
			"info2": "30분 이내",
			"info3": "아무나"
		},
		"ingre": [
			{
				"ingre_name": "치킨너겟",
				"ingre_count": "",
				"ingre_unit": ""
			},
			{
				"ingre_name": "당근",
				"ingre_count": "",
				"ingre_unit": ""
			},
			{
				"ingre_name": "양파",
				"ingre_count": "",
				"ingre_unit": ""
			},
			{
				"ingre_name": "오이",
				"ingre_count": "",
				"ingre_unit": ""
			},
			{
				"ingre_name": "물",
				"ingre_count": "",
				"ingre_unit": ""
			},
			{
				"ingre_name": "전분",
				"ingre_count": "",
				"ingre_unit": ""
			},
			{
				"ingre_name": "물",
				"ingre_count": "300",
				"ingre_unit": "ml"
			},
			{
				"ingre_name": "식초",
				"ingre_count": "4",
				"ingre_unit": "T"
			},
			{
				"ingre_name": "간장",
				"ingre_count": "2",
				"ingre_unit": "T"
			},
			{
				"ingre_name": "설탕",
				"ingre_count": "6",
				"ingre_unit": "T"
			},
			{
				"ingre_name": "굴소스",
				"ingre_count": "1",
				"ingre_unit": "T"
			}
		],
		"recipe": [
			{
				"txt": "재료를 준비한다.",
				"img": "https://recipe1.ezmember.co.kr/cache/recipe/2017/03/24/a632ce4fcdd0066d5e5b37710a92f53b1.png"
			},
			{
				"txt": "야채를 손질한다.",
				"img": "https://recipe1.ezmember.co.kr/cache/recipe/2017/03/24/6dd27ab514592b7af247c3f57221594f1.png"
			},
			{
				"txt": "팬에 기름을 두르고 치킨너겟을 굽는다.",
				"img": "https://recipe1.ezmember.co.kr/cache/recipe/2017/03/24/aca74d53684af60fd31bb09f648374481.png"
			},
			{
				"txt": "냄비에 물과 소스재료를 모두 넣는다.간보고 조금 더 새콤한 맛을 원하신다면 식초1T 추가.",
				"img": "https://recipe1.ezmember.co.kr/cache/recipe/2017/03/24/3e5cc1889b09b2f8978c92680344f6e41.png"
			},
			{
				"txt": "양념이 다 녹았으면 준비한 야채를 넣는다.",
				"img": "https://recipe1.ezmember.co.kr/cache/recipe/2017/03/24/5b1040206a08a3d501870815c6e3ca751.png"
			},
			{
				"txt": "물이 끓으면 물 전분을 조금씩 넣어 농도를 맞춘다.",
				"img": "https://recipe1.ezmember.co.kr/cache/recipe/2017/03/24/e47ea13f32eb45323f561c03af50803f1.png"
			},
			{
				"txt": "구운 치킨너겟 위에 소스를 뿌린다.",
				"img": "https://recipe1.ezmember.co.kr/cache/recipe/2017/03/24/230dc3859867ea92c4ba9f3b8bdeb6821.png"
			}
		]
	},
	{
		"id": 16,
		"name": "[간단 자취요리] 야매 한방 보쌈(수육)! 저렴하게 한방 보쌈을 먹어보자!",
		"img": "https://recipe1.ezmember.co.kr/cache/recipe/2016/05/19/9939ce43bbf38870197e2f0d37cd3bc11.jpg",
		"summary": "오늘은 초간단 재료로 한방 보쌈을 만들어 봤어요 :)자취생분들 족발,보쌈 혼자서 시켜드시기 가격적으로도 부담스러우실 때 많으시잖아요 한약재의 향이 솔솔~ 고급진 한방보쌈을 저렴하게 만들어봅시다참고로 영상에는 삶는시간이 30~40분이라고 명시되어있지만,수육,보쌈을 삶으실때는 뭉근하게 오래 삶으실수록 더 부드러워요",
		"info": {
			"info1": "2인분",
			"info2": "60분 이내",
			"info3": "아무나"
		},
		"ingre": [
			{
				"ingre_name": "삼겹살",
				"ingre_count": "500",
				"ingre_unit": "g"
			},
			{
				"ingre_name": "삼계탕용약재팩",
				"ingre_count": "1",
				"ingre_unit": "개"
			},
			{
				"ingre_name": "물",
				"ingre_count": "",
				"ingre_unit": ""
			},
			{
				"ingre_name": "된장",
				"ingre_count": "2",
				"ingre_unit": "T"
			},
			{
				"ingre_name": "간장",
				"ingre_count": "3",
				"ingre_unit": "T"
			}
		],
		"recipe": [
			{
				"txt": "재료를 준비합니다.",
				"img": "https://recipe1.ezmember.co.kr/cache/recipe/2016/05/19/9c0ddcf0a6dcfe92f8395f20f0d6d92f1.jpg"
			},
			{
				"txt": "한방티백과 양파를 넣습니다.",
				"img": "https://recipe1.ezmember.co.kr/cache/recipe/2016/05/19/9cea1195f381783d5c2b80398eabe07a1.jpg"
			},
			{
				"txt": "된장과 간장도 넣어주세요.",
				"img": "https://recipe1.ezmember.co.kr/cache/recipe/2016/05/19/9a485484ead3db9ed85e11c4478932f51.jpg"
			},
			{
				"txt": "물이 끓으면 준비한 삼겹살을 넣어줍니다.",
				"img": "https://recipe1.ezmember.co.kr/cache/recipe/2016/05/19/e3f2597a3439e94f5ce9a493a54879911.jpg"
			},
			{
				"txt": "뚜껑을 닫고 중불에서 3~40분 뭉근하게 끓여줍니다.",
				"img": "https://recipe1.ezmember.co.kr/cache/recipe/2016/05/19/271df55cb3a5cc612660a9f83bfc36d91.jpg"
			},
			{
				"txt": "중간중간 뒤집어주면 간이 더 고루 잘 베입니다.",
				"img": "https://recipe1.ezmember.co.kr/cache/recipe/2016/05/19/35e7a27e8e5cc0d27d137af99c9b86601.jpg"
			},
			{
				"txt": "젓가락으로 두꺼운 살 부분을 찔러 쉽게 들어가면 익은 것입니다.",
				"img": "https://recipe1.ezmember.co.kr/cache/recipe/2016/05/19/cc86140a3eb7abdc1117d1631934e4531.jpg"
			},
			{
				"txt": "고기를 건져내어 썰어주세요.",
				"img": "https://recipe1.ezmember.co.kr/cache/recipe/2016/05/19/e633a3e6e0afab932f63d1b99966bf771.jpg"
			},
			{
				"txt": "보쌈용 김치와 함께 담으면 완성입니다.",
				"img": "https://recipe1.ezmember.co.kr/cache/recipe/2016/05/19/a095af78a79a00225152afde73e9c63d1.jpg"
			}
		]
	},
	{
		"id": 17,
		"name": "[간단 자취요리] 돼지고기 없이! 더 맛있는 비엔나 카레만들기 ",
		"img": "https://recipe1.ezmember.co.kr/cache/recipe/2016/06/09/549363890f564f9117ea755bd87357321.jpg",
		"summary": "오늘은 돼지고기 없는 카레 / 카레라이스를 만들어봤어요!자취하시는 분들 돼지고기 일인분만 사기도 번거롭고 귀찮죠?그래서 개인적인 입맛으로는 돼지고기 넣은 카레보다 더 맛있는비엔나 카레를 만들어봤습니다* 버터없으시면 식용유 사용하셔도 좋지만,버터가 들어가면 훨씬 풍미작렬!!!!!!* 카레는 제품마다 조금씩 물비율이 다르니, 뒷면을 참조해서넣으시면 돼요! ( 종이컵1컵 = 180ml) 그리고 많이 만들어두시고 일인분씩 락엔락에 넣어서냉동했다가 해동해서 드셔도 좋아요 :)",
		"info": {
			"info1": "3인분",
			"info2": "30분 이내",
			"info3": "아무나"
		},
		"ingre": [
			{
				"ingre_name": "카레분말(or큐브형)",
				"ingre_count": "",
				"ingre_unit": ""
			},
			{
				"ingre_name": "비엔나소세지",
				"ingre_count": "",
				"ingre_unit": ""
			},
			{
				"ingre_name": "감자",
				"ingre_count": "",
				"ingre_unit": ""
			},
			{
				"ingre_name": "양파",
				"ingre_count": "",
				"ingre_unit": ""
			},
			{
				"ingre_name": "당근",
				"ingre_count": "",
				"ingre_unit": ""
			},
			{
				"ingre_name": "버터",
				"ingre_count": "2",
				"ingre_unit": "T"
			}
		],
		"recipe": [
			{
				"txt": "재료를 준비합니다.",
				"img": "https://recipe1.ezmember.co.kr/cache/recipe/2016/06/09/7ef7227e0559b8f8efd9e94a9066eede1.jpg"
			},
			{
				"txt": "양파를 먹기 좋게 썰어주세요.",
				"img": "https://recipe1.ezmember.co.kr/cache/recipe/2016/06/09/480090c9cb3c185bda73e016500a17d51.jpg"
			},
			{
				"txt": "당근도 썰어주시고 돌려깎이는 생략해도 됩니다.",
				"img": "https://recipe1.ezmember.co.kr/cache/recipe/2016/06/09/77363ec053351fca4dd071da3a3a48861.jpg"
			},
			{
				"txt": "감자도 그렇게 썰어주세요.",
				"img": "https://recipe1.ezmember.co.kr/cache/recipe/2016/06/09/62dfc22d6a50bed9d0614871de4f3b121.jpg"
			},
			{
				"txt": "비엔나소시지도 한 입 크기로 썰어주세요.",
				"img": "https://recipe1.ezmember.co.kr/cache/recipe/2016/06/09/09c5e651bbef93e88f0513658cdef81f1.jpg"
			},
			{
				"txt": "버터를 냄비에 녹여주세요. 버터가 없으시면 식용유도 괜찮아요.",
				"img": "https://recipe1.ezmember.co.kr/cache/recipe/2016/06/09/acfaaaf05b9920186e13d18a26ceb8231.jpg"
			},
			{
				"txt": "버터가 녹으면 손질해 둔 채소를 넣고 볶아줍니다.",
				"img": "https://recipe1.ezmember.co.kr/cache/recipe/2016/06/09/702622c60e5321beab08b55ce3021d3e1.jpg"
			},
			{
				"txt": "어느정도 볶다가 소시지도 넣어주세요.",
				"img": "https://recipe1.ezmember.co.kr/cache/recipe/2016/06/09/6a9d983615d0b8c01c684457c13586cb1.jpg"
			},
			{
				"txt": "카레분말을 넣기 전 물을 먼저 넣어주세요. 물의 비율은 구매한 카레 제품의 뒷면을 참조하세요!",
				"img": "https://recipe1.ezmember.co.kr/cache/recipe/2016/06/09/683bde84345b6009a7dd2ca977d2a4c91.jpg"
			},
			{
				"txt": "카레가루는 조금씩 넣어가며 저어줍니다.",
				"img": "https://recipe1.ezmember.co.kr/cache/recipe/2016/06/09/0c0faf45c2151db08613cece8e179a8e1.jpg"
			},
			{
				"txt": "분말을 잘 섞은 카레는 약불에서 보글보글 더 끓여줍니다.",
				"img": "https://recipe1.ezmember.co.kr/cache/recipe/2016/06/09/55ae9935a2c679676bab7dc9e911bfe91.jpg"
			},
			{
				"txt": "비엔나 소시지가 카레에 동동 뜨면 완성입니다.",
				"img": "https://recipe1.ezmember.co.kr/cache/recipe/2016/06/09/ab2eb76eecc71e11cd39034b5af285981.jpg"
			}
		]
	},
	{
		"id": 18,
		"name": "[간단 자취요리] 고추튀김을 이렇게 간단하게? 야매 고추튀김 만들기",
		"img": "https://recipe1.ezmember.co.kr/cache/recipe/2016/06/02/8d386eb4b4109d09a3fb2c6d03618fa51.jpg",
		"summary": "안녕하세요 여러분!! 오늘은 고추튀김을 만들어 봤어요 :)저는 떡볶이랑 같이 튀김을 살때 보통 오징어,고추튀김을 제일 좋아해요!!! :) 그래서 오늘은 초간단 고추튀김 만드는 방법을 알려드릴게요!원래 고추튀김은 속에 다진고기,각종야채,당면,등등만드는 방법이 굉장히 복잡해서 자취생들이 시도하기는 좀 무리가 있어서 냉동만두 소를 이용해 초간단 고추튀김을 만들어 봤어요! 맛도 완전 굿굿!!!고추는 오이고추(아삭이고추) 사용하시면 커서 속넣기 좋아요!!",
		"info": {
			"info1": "2인분",
			"info2": "30분 이내",
			"info3": "아무나"
		},
		"ingre": [
			{
				"ingre_name": "냉동만두",
				"ingre_count": "",
				"ingre_unit": ""
			},
			{
				"ingre_name": "고추",
				"ingre_count": "",
				"ingre_unit": ""
			},
			{
				"ingre_name": "튀김가루",
				"ingre_count": "",
				"ingre_unit": ""
			},
			{
				"ingre_name": "물",
				"ingre_count": "",
				"ingre_unit": ""
			}
		],
		"recipe": [
			{
				"txt": "재료를 준비합니다.",
				"img": "https://recipe1.ezmember.co.kr/cache/recipe/2016/06/02/e7df81d3bc0997a466f6d10acfe7052c1.jpg"
			},
			{
				"txt": "냉동만두를 전자레인지로 해동해주세요.전자레인지",
				"img": "https://recipe1.ezmember.co.kr/cache/recipe/2016/06/02/5836d947557b8d20db8221724edec00f1.jpg"
			},
			{
				"txt": "해동한 만두는 만두피를 벗겨주세요.",
				"img": "https://recipe1.ezmember.co.kr/cache/recipe/2016/06/02/4ac70c63f6a361bdca0378c6efb0a46e1.jpg"
			},
			{
				"txt": "만두소는 다시 잘 비벼줍니다.",
				"img": "https://recipe1.ezmember.co.kr/cache/recipe/2016/06/02/e94b77c2ddaafbf0b0e711cc89a3ca8d1.jpg"
			},
			{
				"txt": "고추는 배를 갈라 씨를 빼주세요.",
				"img": "https://recipe1.ezmember.co.kr/cache/recipe/2016/06/02/828d9c3305ec31858f7e10ee320a516e1.jpg"
			},
			{
				"txt": "고추의 속에 튀김가루를 발라줍니다.",
				"img": "https://recipe1.ezmember.co.kr/cache/recipe/2016/06/02/57412dd16fb0ecf3a23c1d4e9f7f813f1.jpg"
			},
			{
				"txt": "고추 속에 만두소를 넣어주세요.",
				"img": "https://recipe1.ezmember.co.kr/cache/recipe/2016/06/02/ae0e9b38d2e68d3daffde7e6fbd2dbfe1.jpg"
			},
			{
				"txt": "튀김가루에 얼음물을 섞어주세요.",
				"img": "https://recipe1.ezmember.co.kr/cache/recipe/2016/06/02/bdc116872f820ef0e5ad9981a400bddc1.jpg"
			},
			{
				"txt": "물을 한 번에 넣지 않고 농도를 확인하며 만들어 주세요.",
				"img": "https://recipe1.ezmember.co.kr/cache/recipe/2016/06/02/8023adb60e5b75ce98a0e5da74b3f6911.jpg"
			},
			{
				"txt": "튀김물을 고추에 꼼꼼하게 발라줍니다.",
				"img": "https://recipe1.ezmember.co.kr/cache/recipe/2016/06/02/5532ce90f37522abe97979e1b367128f1.jpg"
			},
			{
				"txt": "후라이팬에 기름을 붓고 중불에서 노릇하게 튀겨주세요.",
				"img": "https://recipe1.ezmember.co.kr/cache/recipe/2016/06/02/485625c9481f22c12bbb4af4188a19ab1.jpg"
			},
			{
				"txt": "적당히 익은 고추튀김은 키친타올에 두어 기름을 빼줍니다.",
				"img": "https://recipe1.ezmember.co.kr/cache/recipe/2016/06/02/fb33cd7043df48833652c3fd447490341.jpg"
			}
		]
	},
	{
		"id": 19,
		"name": "대패삼겹살 숙주볶음 만들기 도시락반찬 초간단 자취생요리",
		"img": "https://recipe1.ezmember.co.kr/cache/recipe/2021/03/10/7b96ee5131085eb09a5abd428295d9a01.jpg",
		"summary": "맛있는 대패삼겹살 숙주볶음 만들어 볼께요.,",
		"info": {
			"info1": "4인분",
			"info2": "20분 이내",
			"info3": "아무나"
		},
		"ingre": [
			{
				"ingre_name": "대패삼겹살",
				"ingre_count": "150",
				"ingre_unit": "g"
			},
			{
				"ingre_name": "숙주",
				"ingre_count": "1/2",
				"ingre_unit": "봉"
			},
			{
				"ingre_name": "진간장",
				"ingre_count": "1.",
				"ingre_unit": ".T"
			},
			{
				"ingre_name": "굴소스",
				"ingre_count": "1",
				"ingre_unit": "T"
			},
			{
				"ingre_name": "후추",
				"ingre_count": "",
				"ingre_unit": "약간"
			},
			{
				"ingre_name": "고추",
				"ingre_count": "1",
				"ingre_unit": "움큼"
			},
			{
				"ingre_name": "마늘",
				"ingre_count": "2",
				"ingre_unit": "개"
			},
			{
				"ingre_name": "양파",
				"ingre_count": "1/2",
				"ingre_unit": "개"
			}
		],
		"recipe": [
			{
				"txt": "초간단 숙주대패삼겹살 볶음 만들어 볼께요.",
				"img": "https://recipe1.ezmember.co.kr/cache/recipe/2021/03/10/59752f8da18ff6ada0c4e9bfa358bad91.jpg"
			},
			{
				"txt": "기름을 두르고 마늘을 볶아서 마늘 기름을 내 주세요.",
				"img": "https://recipe1.ezmember.co.kr/cache/recipe/2021/03/10/6e85a4ad0e8f37ef4ada2bd5a70b44fb1.jpg"
			},
			{
				"txt": "그리고 대패삼겹살이 어느정도 다 익었다 싶으시면",
				"img": "https://recipe1.ezmember.co.kr/cache/recipe/2021/03/10/5d62a2c5a1267a32de49c9cc0327897a1.jpg"
			},
			{
				"txt": "진간장1.5T.굴소스 1T.후추약간.고추 한움큼.마늘2개을 넣고 잘 섞으면서 볶아 주세요.",
				"img": "https://recipe1.ezmember.co.kr/cache/recipe/2021/03/10/32ac3636c9be445ad2ef3c577c6ec7451.jpg"
			},
			{
				"txt": "그리고 양념이 배도록 섞으면서 고추 썰어둔거나 파를 넣으셔도 좋아요. 양파 고추와 숙주를 넣고  고기가 다 익은 거라서 숙주의 아삭한 식감이 살아 있을 정도로 너무 흐물 흐물 해지지 않을 정도로  휘리릭 ~~~~~~~~ 볶아 주세요.",
				"img": "https://recipe1.ezmember.co.kr/cache/recipe/2021/03/10/8fc0e287bed0d1e1ceb9719eeea00b271.jpg"
			},
			{
				"txt": "그럼 맛있는 대패삼겹살 숙주볶음이 완성이랍니다.",
				"img": "https://recipe1.ezmember.co.kr/cache/recipe/2021/03/10/b63609b6a745066ab3350c2ca1485ff11.jpg"
			}
		]
	},
	{
		"id": 20,
		"name": "총각김치꽁치조림 간단히 만드는 자취요리",
		"img": "https://recipe1.ezmember.co.kr/cache/recipe/2021/02/20/f185e21d82e734c98358e9dd5ccec60f1.jpg",
		"summary": "꽁치통조림으로 간단히 만들어 본 총각김치꽁치조림이에요.묵은 총각김치가 많아 요즘 자주 만들어 먹고 있는 메뉴랍니다.뭉근하게 끓여낸 총각김치가 너무 맛있어요.무와는 다른 아삭한 식감이 정말 좋아요.",
		"info": {
			"info1": "2인분",
			"info2": "60분 이내",
			"info3": "아무나"
		},
		"ingre": [
			{
				"ingre_name": "꽁치통조림",
				"ingre_count": "2",
				"ingre_unit": "캔"
			},
			{
				"ingre_name": "묵은총각김치",
				"ingre_count": "1",
				"ingre_unit": "대접"
			},
			{
				"ingre_name": "청양고추",
				"ingre_count": "2",
				"ingre_unit": "개"
			},
			{
				"ingre_name": "홍고추",
				"ingre_count": "1",
				"ingre_unit": "개"
			},
			{
				"ingre_name": "양파",
				"ingre_count": "1",
				"ingre_unit": "개"
			},
			{
				"ingre_name": "대파",
				"ingre_count": "1/2",
				"ingre_unit": "대"
			},
			{
				"ingre_name": "김치국물",
				"ingre_count": "1",
				"ingre_unit": "국자"
			},
			{
				"ingre_name": "국간장",
				"ingre_count": "1",
				"ingre_unit": "큰술"
			},
			{
				"ingre_name": "물",
				"ingre_count": "300~400ml",
				"ingre_unit": "~ml"
			},
			{
				"ingre_name": "설탕",
				"ingre_count": "1",
				"ingre_unit": "큰술"
			}
		],
		"recipe": [
			{
				"txt": "양파는 슬라이스로 잘라 주세요",
				"img": "https://recipe1.ezmember.co.kr/cache/recipe/2021/02/20/ee83bb9f72a089a4dbdef4b2047d2ccf1.jpg"
			},
			{
				"txt": "대파는 어슷썰어준비합니다.",
				"img": "https://recipe1.ezmember.co.kr/cache/recipe/2021/02/20/5c811eecdbad9eeac8a893564401113d1.jpg"
			},
			{
				"txt": "청양고추와 홍고추도 쫑쫑 썰어주세요",
				"img": "https://recipe1.ezmember.co.kr/cache/recipe/2021/02/20/aa919c7c5a1f5cf7d7de4ece1d6fccf21.jpg"
			},
			{
				"txt": "냄비에 총각김치를 깔아주세요총각김치를 좋아해서 저는 많이 넣어줬어요. 적당하게 넣고 싶으시면 보이는 양의 반으로 줄이셔도 좋아요.",
				"img": "https://recipe1.ezmember.co.kr/cache/recipe/2021/02/20/d46967029d9f1b2838bb1261f78e9a581.jpg"
			},
			{
				"txt": "꽁치를 올려줍니다국물까지 다 넣어주세요.국물에 간이 있어서 같이 들어가야 맛있어요.",
				"img": "https://recipe1.ezmember.co.kr/cache/recipe/2021/02/20/fdc94ac05846692502202405a5e815181.jpg"
			},
			{
				"txt": "썰어놓은 채소들과 고춧가루를 뿌려주세요. 그 다음 물을 넣어줍니다.꽁치캔국물이 있어서 육수를 쓰지 않고 맹물을 써도 국물에 감칠맛이 납니다.",
				"img": "https://recipe1.ezmember.co.kr/cache/recipe/2021/02/20/ca39ee2f86d97b245d5eb094d15db9ff1.jpg"
			},
			{
				"txt": "뚜껑을 닫고 끓여줍니다.강불",
				"img": "https://recipe1.ezmember.co.kr/cache/recipe/2021/02/20/63779df86643afee047667c271f0e5111.jpg"
			},
			{
				"txt": "국물이 끓어오르면 중약불로 내려 15분~20분 뭉근하게 끓여주세요.중약불뭉근하게 끓여줘야 무가 잘 익어요.중간중간 국물을 끼얹어 가며 끓여주세요.",
				"img": "https://recipe1.ezmember.co.kr/cache/recipe/2021/02/20/33bae8bcfd64f44ede1aac6e5516437f1.jpg"
			},
			{
				"txt": "색이 빨갛게 나지 않는다면 고춧가루 1/2큰술을  추가해주셔도 좋아요.",
				"img": "https://recipe1.ezmember.co.kr/cache/recipe/2021/02/20/c98a180027a34c9432aa47f998537ea41.jpg"
			},
			{
				"txt": "뚜껑을 닫고 중약불로 끓여주다 무가 어느정도 익었다면 대파를 올여줍니다.",
				"img": "https://recipe1.ezmember.co.kr/cache/recipe/2021/02/20/2f0696b28cb57947ce178eae126b6c831.jpg"
			},
			{
				"txt": "한소끔 끓여주고 모자란간은 소금을 넣어  간을 맞춰줍니다.저는 더 간을 하지 않았어요.",
				"img": "https://recipe1.ezmember.co.kr/cache/recipe/2021/02/20/a0635f719998bb63fa77c83e6226d12a1.jpg"
			},
			{
				"txt": "꽁치캔과 묵은 총각김치로 간단하게 끓여낸 총각김치 꽁치조림이에요.말캉하게 씹히는 무와 고소한 꽁치가 정말 맛있어요.",
				"img": "https://recipe1.ezmember.co.kr/cache/recipe/2021/02/20/1e72d78cc9f34b075a42ccb44dc639861.jpg"
			},
			{
				"txt": "캔이라 비린내도 나지않아 초보도 간단하게 끓일 수 있는 자취요리입니다.집에 묵은 총각김치가 있다면 이렇게 끓여보세요.물에 말아서 같이 먹어도  정말 맛있어요.",
				"img": "https://recipe1.ezmember.co.kr/cache/recipe/2021/02/20/b2e86af02c8d90fb8056a21ce62bfff51.jpg"
			}
		]
	},
	{
		"id": 21,
		"name": "[자취 요리] 간단하지만 보기 좋은 자취생 손님맞이 요리 밀푀유나베 레시피!",
		"img": "https://recipe1.ezmember.co.kr/cache/recipe/2021/02/06/5a19ccc50b02ffa49b087b669973f0a61.jpg",
		"summary": "손님이 집에 놀러오셨을 때, 자취생들은 참 난감하죠?배달음식을 시켜놓자니 정성이 없어보이고, 손님들의 입맛을 사로잡기엔 아직 렙업이 덜 되어있는 나의 요리실력 ㅠㅠ오늘은 초보자도 누구든 할 수 있고 호불호도 없지만 너무 예뻐서 있어보이는 손님맞이 대표음식 '밀푀유나베' 만드는 방법을 공유하겠습니다^^",
		"info": {
			"info1": "3인분",
			"info2": "15분 이내",
			"info3": "아무나"
		},
		"ingre": [
			{
				"ingre_name": "소고기불고기또는샤브용",
				"ingre_count": "300",
				"ingre_unit": "g"
			},
			{
				"ingre_name": "깻잎",
				"ingre_count": "20~40장",
				"ingre_unit": "~장"
			},
			{
				"ingre_name": "배추",
				"ingre_count": "10",
				"ingre_unit": "장"
			},
			{
				"ingre_name": "만가닥버섯",
				"ingre_count": "1",
				"ingre_unit": "팩"
			},
			{
				"ingre_name": "계란노른자",
				"ingre_count": "1",
				"ingre_unit": "개"
			},
			{
				"ingre_name": "오리엔탈소스",
				"ingre_count": "5",
				"ingre_unit": "큰술"
			}
		],
		"recipe": [
			{
				"txt": "먼저 재료들이 몸을 담굴 육수를 끓여 준비합니다^^ 저는 시판 샤브샤브용 육수를 이용했어요 !! 샤브샤브용 육수가 싫으신 분들은 1) 멸치 3마리, 다시마 2장, 대파 또는 파뿌리를 넣고 펄펄 끓을 때까지 끓여주시다가  2) 모두 건져내고 간장 1큰술을 넣어주시면  육수가 완성됩니당 ㅎㅎ멸치(디포리)3마리, 다시마, 연두, 강불육수재료들을 한꺼번에 한 팩에 넣어놓은 시판 육수팩을 이용하시면 훨~씬 간편해요^^",
				"img": "https://recipe1.ezmember.co.kr/cache/recipe/2021/02/06/b9131358070e5cbfa50e285fa3070eed1.jpg"
			},
			{
				"txt": "배추, 깻잎, 버섯을 씻어줍니다! 1. 배춧잎 수의 2배만큼 깻잎을 준비해주세요 2. 버섯은 취향에 맞게!!  단, 손님접대용이라면 [팽이버섯, 만가닥버섯(흰색, 갈색 둘 다), 표고버섯 1개] 저는 만가닥버섯을 좋아해서 이번에는 만가닥버섯으로만배추, 깻잎, 버섯배추는 햄버거처럼 합쳐질거라 되도록 크기가 비슷한 것들로 준비해주시는게 보기에도 먹기에도 좋아요^^",
				"img": "https://recipe1.ezmember.co.kr/cache/recipe/2021/02/06/2c9e67422a3da47d502fa1ff0bd92d741.jpg"
			},
			{
				"txt": "재료들을 '배추 => 깻잎 => 고기 => 깻잎 => 배추' 순으로 쌓아줍니다!!샤브샤브용 고기를 이용하시는 분들은 고기를 두 번 쌓아주셔도 좋아요^^",
				"img": "https://recipe1.ezmember.co.kr/cache/recipe/2021/02/06/4af8f8a9d3cd3b76ffdfed0e8439887c1.jpg"
			},
			{
				"txt": "자 이제 거의 마지막 단계인데요~ 준비한 재료를 3등분으로 자르고 겹쳐줍니다",
				"img": "https://recipe1.ezmember.co.kr/cache/recipe/2021/02/06/e035a7717d194354207d6d3349d43be01.jpg"
			},
			{
				"txt": "넓적한 팬이나 냄비에 잘라놓은 재료를 차곡차곡 쌓아주고 가운데에 준비한 버섯을 채워주세요! 그리고 맨 처음 준비해두었던 육수를 넣고 재료들이 익을 때까지 끓여주면 완성~",
				"img": "https://recipe1.ezmember.co.kr/cache/recipe/2021/02/06/918b64b73254d50880b269b35766553c1.jpg"
			},
			{
				"txt": "취향에 맞게 드시면 되지만 저는  '오리엔탈소스(샐러드소스) + 노른자 조합'을 강추드립니다!! 그 외에도 노른자의 비린 맛을 싫어하시는 분들은 - 집에있는 짱아찌 국물에 피넛버터를 넣어서 섞거나  - 시판 스위트칠리 소스를 곁들여 먹는 것도 맛있어요^^노른자 분리가 어려우신 분들은 빈 페트병 입구를 계란 노른자에 맞춰 대고 손으로 페트병을 살짝 눌렀다 떼시면 됩니당 ㅎㅎㅎ",
				"img": "https://recipe1.ezmember.co.kr/cache/recipe/2021/02/06/34c7063e1d9e3fa41f2a16c044fca6831.jpg"
			}
		]
	},
	{
		"id": 22,
		"name": "[간단 자취요리] 치킨인 척. 양반 후반 어묵 튀김 만들기",
		"img": "https://recipe1.ezmember.co.kr/cache/recipe/2017/12/26/c4b24c87dc064ab14c98cca5de7214101.jpg",
		"summary": "안녕하세요 얌배추들!!!오늘은 양반 후반 치킨을 닮은 양반 후반 어묵 튀김입니다 :D길쭉이 어묵으로 간단하게 만들어 봤어요! 참! 뒷부분에 먹는 소리가 좋다는 의견이 많아 조금 늘려봤습니다.",
		"info": {
			"info1": "2인분",
			"info2": "15분 이내",
			"info3": "초급"
		},
		"ingre": [
			{
				"ingre_name": "일자어묵",
				"ingre_count": "7",
				"ingre_unit": "개"
			},
			{
				"ingre_name": "튀김가루",
				"ingre_count": "1",
				"ingre_unit": "cup"
			},
			{
				"ingre_name": "케찹",
				"ingre_count": "4",
				"ingre_unit": "T"
			},
			{
				"ingre_name": "고추장",
				"ingre_count": "1",
				"ingre_unit": "T"
			},
			{
				"ingre_name": "다진마늘",
				"ingre_count": "2",
				"ingre_unit": "T"
			},
			{
				"ingre_name": "간장",
				"ingre_count": "1",
				"ingre_unit": "T"
			},
			{
				"ingre_name": "설탕",
				"ingre_count": "5",
				"ingre_unit": "T"
			},
			{
				"ingre_name": "올리고당",
				"ingre_count": "4",
				"ingre_unit": "T"
			},
			{
				"ingre_name": "물",
				"ingre_count": "1/2",
				"ingre_unit": "컵"
			}
		],
		"recipe": [
			{
				"txt": "먼저 어묵을 한 입 크기로 썰어주세요!",
				"img": "https://recipe1.ezmember.co.kr/cache/recipe/2017/12/26/a55ade88ab916a48319c84a0428d0eec1.png"
			},
			{
				"txt": "튀김가루에 물을 넣고 반죽을 만들어 주세요. 물을 조금씩 넣어가며 농도를 맞춰주세요!",
				"img": "https://recipe1.ezmember.co.kr/cache/recipe/2017/12/26/273f37b9a461ea130258f8f8e67bdff31.png"
			},
			{
				"txt": "어묵을 넣고 잘 비벼주세요.",
				"img": "https://recipe1.ezmember.co.kr/cache/recipe/2017/12/26/eddea9d07db2eb046c3f83cfde4f7c301.png"
			},
			{
				"txt": "비닐팩에 튀김가루, 어묵을 넣고 흔들어줍니다!",
				"img": "https://recipe1.ezmember.co.kr/cache/recipe/2017/12/26/88c5320c3a86e8a298d83b70ea019a791.png"
			},
			{
				"txt": "튀겨줍니다.(처음엔 중불, 다 넣고 약불)",
				"img": "https://recipe1.ezmember.co.kr/cache/recipe/2017/12/26/3668becdb70ce88a2572e1eb97cd30261.png"
			},
			{
				"txt": "어묵이 부풀면 다 된거예요!",
				"img": "https://recipe1.ezmember.co.kr/cache/recipe/2017/12/26/e6b72725248dc19493e8d98b55e5f66d1.png"
			},
			{
				"txt": "양념들을 넣고 양념치킨 소스를 만듭시다. 약불에 졸여주세요!",
				"img": "https://recipe1.ezmember.co.kr/cache/recipe/2017/12/26/1393f8d7c120cf1d7c0a7f53fe0c57151.png"
			},
			{
				"txt": "농도 확인!",
				"img": "https://recipe1.ezmember.co.kr/cache/recipe/2017/12/26/4a29f021b8fb75176819248358cc6bf31.png"
			},
			{
				"txt": "튀긴 어묵 반을 넣고 버무려줍니다.약불",
				"img": "https://recipe1.ezmember.co.kr/cache/recipe/2017/12/26/8e231f7968d9d7d937a927b552953a031.png"
			}
		]
	},
	{
		"id": 23,
		"name": "[간단 자취요리] 생선조림이 그리울 때 바로 이 레시피! / 참치조림 만들기 / 참치캔 요리",
		"img": "https://recipe1.ezmember.co.kr/cache/recipe/2017/08/10/5243ae7d8adc82916746f0e127fa26581.jpg",
		"summary": "안녕하세요 여러분!!자취생들은 생선구이나 생선조림을 먹고 싶어도 비린내나 뒤처리의 어려움 등으로 꺼리시는 분들이 많죠?그래서 오늘은 간단하게 참치캔으로 그 맛을 내봤습니닷!사실 저도 이렇게 해먹은건 처음인데 생각해보니까 참치도 생선이잖아요...? :D",
		"info": {
			"info1": "1인분",
			"info2": "15분 이내",
			"info3": "초급"
		},
		"ingre": [
			{
				"ingre_name": "참치",
				"ingre_count": "1",
				"ingre_unit": "캔"
			},
			{
				"ingre_name": "감자",
				"ingre_count": "1",
				"ingre_unit": "개"
			},
			{
				"ingre_name": "양파",
				"ingre_count": "1/2",
				"ingre_unit": "개"
			},
			{
				"ingre_name": "물",
				"ingre_count": "300",
				"ingre_unit": "ml"
			},
			{
				"ingre_name": "고춧가루",
				"ingre_count": "3",
				"ingre_unit": "T"
			},
			{
				"ingre_name": "간장",
				"ingre_count": "2~3T",
				"ingre_unit": "~T"
			},
			{
				"ingre_name": "다진마늘",
				"ingre_count": "1",
				"ingre_unit": "T"
			},
			{
				"ingre_name": "된장",
				"ingre_count": "1",
				"ingre_unit": "T"
			},
			{
				"ingre_name": "물",
				"ingre_count": "2~3T",
				"ingre_unit": "~T"
			}
		],
		"recipe": [
			{
				"txt": "먼저 양파를 굵게 썰어줍니다:D",
				"img": "https://recipe1.ezmember.co.kr/cache/recipe/2017/08/10/623e4e9a4673d3b3276e811010ba75ec1.jpg"
			},
			{
				"txt": "감자도 굵게 썰어줍니다.",
				"img": "https://recipe1.ezmember.co.kr/cache/recipe/2017/08/10/00c6e2d9f98df31003e2a9c0493469a31.jpg"
			},
			{
				"txt": "양념을 모두 섞어 양념장을 만들어주세요.",
				"img": "https://recipe1.ezmember.co.kr/cache/recipe/2017/08/10/d66fe0f20b90a126c71cb5be028c904b1.jpg"
			},
			{
				"txt": "감자를 깔고 물을 넣고 끓여줍니다.",
				"img": "https://recipe1.ezmember.co.kr/cache/recipe/2017/08/10/4670adcd7dc86969fba2fb7e57670c581.jpg"
			},
			{
				"txt": "감자가 살짝익으면 양파, 참치(국물도), 양념을 넣어줘요!",
				"img": "https://recipe1.ezmember.co.kr/cache/recipe/2017/08/10/c30bb1e69260f9e090f8fcb61dbb44f51.jpg"
			},
			{
				"txt": "중약불에서 지글지글 끓여줘요!",
				"img": "https://recipe1.ezmember.co.kr/cache/recipe/2017/08/10/07027d480fd88abacc615430d02535c61.jpg"
			}
		]
	},
	{
		"id": 24,
		"name": "[간단 자취요리] 깐쇼새우 저렴이 버전! 깐쇼 팝만두 만들기",
		"img": "https://recipe1.ezmember.co.kr/cache/recipe/2017/06/28/74105f5ee80bb48458e1ac1faf67ad1a1.jpg",
		"summary": "안녕하세요 여러분!!오늘은 깐쇼새우의 자취버전, 저렴이 버전인 깐쇼 팝만두를 준비했어요 :D지난번에 깐쇼새우를 업로드했었죠?새우를 못드시거나 사정상 새우를 구하기가 어려운 친구들도 있을 것 같아서, 그 때부터 두가지 버전을 계획하고 있다가 오늘 업로드 합니다!",
		"info": {
			"info1": "1인분",
			"info2": "30분 이내",
			"info3": "아무나"
		},
		"ingre": [
			{
				"ingre_name": "물만두",
				"ingre_count": "15~20개",
				"ingre_unit": "~개"
			},
			{
				"ingre_name": "케찹10T(종이컵1/2컵)",
				"ingre_count": "10T(종이컵1/2컵)",
				"ingre_unit": "T(종이컵컵)"
			},
			{
				"ingre_name": "다진마늘",
				"ingre_count": "1",
				"ingre_unit": "T"
			},
			{
				"ingre_name": "설탕",
				"ingre_count": "3",
				"ingre_unit": "T"
			},
			{
				"ingre_name": "물",
				"ingre_count": "1/2~1컵",
				"ingre_unit": "~컵"
			},
			{
				"ingre_name": "전분10T(종이컵1/2컵)",
				"ingre_count": "10T(종이컵1/2컵)",
				"ingre_unit": "T(종이컵컵)"
			},
			{
				"ingre_name": "물",
				"ingre_count": "6~8T",
				"ingre_unit": "~T"
			}
		],
		"recipe": [
			{
				"txt": "먼저 물만두를 전자레인지로 해동해줍니다.전자레인지",
				"img": "https://recipe1.ezmember.co.kr/cache/recipe/2017/06/28/3a21e68d8800abde2ae2a5946e87673d1.png"
			},
			{
				"txt": "전분에 물을 조금씩 섞어 반죽을 만듭니다.약간 묽게 만들어주세요!",
				"img": "https://recipe1.ezmember.co.kr/cache/recipe/2017/06/28/2c95bf8d2e96fdb586a6adb34d30f04c1.png"
			},
			{
				"txt": "만두에 반죽을 묻히고 튀겨줍니다.",
				"img": "https://recipe1.ezmember.co.kr/cache/recipe/2017/06/28/afcd0cf5de2acc8526cdc89d05dcea6d1.png"
			},
			{
				"txt": "잘 뒤집어가며 맛있게 튀겨주세요 :D중불",
				"img": "https://recipe1.ezmember.co.kr/cache/recipe/2017/06/28/4d6f60b8cdf89eba300de203fddc4bf01.png"
			},
			{
				"txt": "이제 양념을 넣고 모두 조려주세요.깐쇼새우 때보다 조금 더 걸쭉하게 조려주세요!깐쇼새우 만들기",
				"img": "https://recipe1.ezmember.co.kr/cache/recipe/2017/06/28/94bd021b19844dadccb267c3c42e48c91.png"
			},
			{
				"txt": "튀겨놓은 만두를 버무려주세요.최고약불",
				"img": "https://recipe1.ezmember.co.kr/cache/recipe/2017/06/28/80955468d429959f91221f2c8bdb65a31.png"
			}
		]
	},
	{
		"id": 25,
		"name": "[간단 자취요리] 저장식량 대량생산! 바삭 옛날 돈가스 만들기",
		"img": "https://recipe1.ezmember.co.kr/cache/recipe/2017/03/16/01caada45c2fcfe1455a88ca97ed62d91.jpg",
		"summary": "안녕하세요 여러분 :D오늘은 여러분들과 함께 돈가스를 만들어볼거예요이 메뉴는 제가 되게 어렸을 때부터 집에서 어머니와 함께만들면서 지금까지 자주 만들어 먹는 요리인데요~지금은 아이들 촉감놀이(?) 같은거 많이들 하던데제가 어렸을 때는 따로 그런게 없었어요지금 생각해보면 저도 촉감놀이 비슷한 것들을 하면서 자랐네요 :D자취하시는데 계란후라이외에 요리를 안한다 하시는 분들도이거 만들어두시면 요긴하게 먹을 수 있어요!냉동식품 구워먹듯이 그냥 한끼에 한장씩 꺼내서 구워드시면 됩니다그냥 냉동식품 돈가스 사먹지~ 하는 분들도 계실텐데만들어 보세요. 급이 다른 맛입니다ㅋㅋㅋ",
		"info": {
			"info1": "2인분",
			"info2": "30분 이내",
			"info3": "초급"
		},
		"ingre": [
			{
				"ingre_name": "돈가스용등심or안심",
				"ingre_count": "600",
				"ingre_unit": "g"
			},
			{
				"ingre_name": "계란",
				"ingre_count": "2",
				"ingre_unit": "개"
			},
			{
				"ingre_name": "밀가루",
				"ingre_count": "",
				"ingre_unit": ""
			},
			{
				"ingre_name": "빵가루",
				"ingre_count": "",
				"ingre_unit": ""
			},
			{
				"ingre_name": "소금",
				"ingre_count": "",
				"ingre_unit": ""
			},
			{
				"ingre_name": "후추",
				"ingre_count": "",
				"ingre_unit": ""
			}
		],
		"recipe": [
			{
				"txt": "재료를 준비한다.",
				"img": "https://recipe1.ezmember.co.kr/cache/recipe/2017/03/16/db6723773a367a2f08acbcf02ddf82ff1.png"
			},
			{
				"txt": "먼저 등심을 칼등으로 앞 뒤 골고루 한번씩 두드려준다.# 돈가스용 고기는 보통 안심, 등심을 사용하는데요~ 안심이 조금 더 비싸고 부드러운 식감이라면 등심은 조금 더 '고기'스러운 맛과 식감입니다 (질기지는 않아요) 저는 등심을 사용했어요! 600g에 6000원 정도에 샀어요!",
				"img": "https://recipe1.ezmember.co.kr/cache/recipe/2017/03/16/2e1358f717de11df6548d31f49824be11.png"
			},
			{
				"txt": "앞,뒷면에 소금과 후추를 솔솔 뿌려준다.",
				"img": "https://recipe1.ezmember.co.kr/cache/recipe/2017/03/16/5fe31ccfdd9733282b207f4942dd685c1.png"
			},
			{
				"txt": "밀가루->계란->빵가루 순으로 묻혀준다.# 빵가루는 꾹꾹 눌러가면서 꼼꼼하게 묻혀주세요! 빵가루를 묻힐 때 꾹꾹 누르면 누를수록 돈가스가 커집니다 대신 얇아져요ㅎㅎ 적당하게 눌러주시는게 좋겠죠?",
				"img": "https://recipe1.ezmember.co.kr/cache/recipe/2017/03/16/f4754f4f34144b9d258b7adf1442a93f1.png"
			},
			{
				"txt": "팬에 기름을 붓고 튀긴다.# 돈가스를 구우실 때는 적어도 기름이 돈가스의 반정도는 잠기는게 좋습니다 그리고 가장자리 너무 잘 타요 ! 중불~약불 사이에서 자주 뒤집어가며 구우세요 기름 아끼는법은 알죠? 손바닥만한 작은 팬 하나 사셔서 튀김용으로 쓰세요. 기름이 거의 2배는 절약됩니다.( 일반 사이즈 팬에 돈가스가 반 잠기도록 기름을 부으려면 엄청 넣어야겠죠..?)",
				"img": "https://recipe1.ezmember.co.kr/cache/recipe/2017/03/16/b49a0037c01c3dd6bfba37f62b9665d51.png"
			},
			{
				"txt": "튀긴 돈가스에 시판 돈가스 소스를 뿌린다.",
				"img": "https://recipe1.ezmember.co.kr/cache/recipe/2017/03/16/11a34f13c3aaafbec180fe82375c7d151.png"
			},
			{
				"txt": "보관법: 밀폐용기에 비닐팩을 깔고 사이사이에 돈가스를 넣어준다.# 비닐팩이나 랩은 꼭! 깔아주셔야 얼고나서도 서로 붙지 않아요",
				"img": "https://recipe1.ezmember.co.kr/cache/recipe/2017/03/16/385d0001a0c96205117d13dc6d3d07b41.png"
			}
		]
	},
	{
		"id": 26,
		"name": "[간단 자취요리] 탕수육 + 초간단 야매소스 만들기 꿀팁!",
		"img": "https://recipe1.ezmember.co.kr/cache/recipe/2016/07/04/eb90ed2f7cab5aa5ea2a995ebd9f3c521.jpg",
		"summary": "안녕하세요 여러분!! 씬나는 토요일입니다 룰루랄ㄹ라 ♬오늘 하루도 즐겁게 잘 보내셨나요?오늘은 탕수육을 만들어봤어요! 그리고 탕수육은 보통 탕수육 자체보다 소스를 어려워하시는 분들이 굉장히 많은데요!그래서 오늘은 탕수육 소스 초간단으로 만드는 꿀팁 알려드릴게요안에 들어가는 야채는 그냥 냉장고에 있는 야채 쓰시면 됩니다!",
		"info": {
			"info1": "2인분",
			"info2": "30분 이내",
			"info3": "초급"
		},
		"ingre": [
			{
				"ingre_name": "탕수육용고기(등심)",
				"ingre_count": "300",
				"ingre_unit": "g"
			},
			{
				"ingre_name": "전분가루(반죽/물전분)",
				"ingre_count": "",
				"ingre_unit": ""
			},
			{
				"ingre_name": "소금",
				"ingre_count": "1/3",
				"ingre_unit": "T"
			},
			{
				"ingre_name": "후추",
				"ingre_count": "1/4",
				"ingre_unit": "T"
			},
			{
				"ingre_name": "다진마늘(고기밑간)",
				"ingre_count": "1/2",
				"ingre_unit": "T"
			},
			{
				"ingre_name": "계란흰자",
				"ingre_count": "1",
				"ingre_unit": "개"
			},
			{
				"ingre_name": "오렌지주스작은1통(350ml)",
				"ingre_count": "1통(350ml)",
				"ingre_unit": "통(ml)"
			},
			{
				"ingre_name": "물100g(종이컵반컵)",
				"ingre_count": "100g(종이컵반컵)",
				"ingre_unit": "g(종이컵반컵)"
			},
			{
				"ingre_name": "소금",
				"ingre_count": "1/3",
				"ingre_unit": "T"
			},
			{
				"ingre_name": "각종야채",
				"ingre_count": "",
				"ingre_unit": "적당량"
			}
		],
		"recipe": [
			{
				"txt": "재료를 준비합니다.[주 재료]탕수육용 고기(등심)300g, 전분가루(반죽/물전분), 소금1/3T, 후추1/4T, 다진마늘1/2T (고기밑간), 계란 흰자 1개[탕수육소스]오렌지주스 작은1통(350ml), 물100g(종이컵반컵) 설탕1T, 소금1/3T",
				"img": "https://recipe1.ezmember.co.kr/cache/recipe/2016/07/04/5e0021b74ba9e885407f190751124ff81.png"
			},
			{
				"txt": "전분가루에 물을 섞은 뒤 20분 정도 재워둡니다.",
				"img": "https://recipe1.ezmember.co.kr/cache/recipe/2016/07/04/88bd79ec4fe4d1fbe4142a981b3ac73b1.png"
			},
			{
				"txt": "고기에 소금,후추,다진마늘로 밑간을 하고 섞어줍니다.",
				"img": "https://recipe1.ezmember.co.kr/cache/recipe/2016/07/04/0b92cb9176775bf671fea8ddb3ec9ca41.png"
			},
			{
				"txt": "여러야채를 깍뚝깍뚝 썰어줍니다.",
				"img": "https://recipe1.ezmember.co.kr/cache/recipe/2016/07/04/53835d97353c5cc91771aad804998a571.png"
			},
			{
				"txt": "기름을 두른 팬에 야채를 살짝 볶아줍니다.",
				"img": "https://recipe1.ezmember.co.kr/cache/recipe/2016/07/04/1bbbfaf8b388b2b2190323fe52f6d10d1.png"
			},
			{
				"txt": "살짝 볶은 뒤, 오렌지주스,물을 넣어줍니다.",
				"img": "https://recipe1.ezmember.co.kr/cache/recipe/2016/07/04/d36ab84414480169a6b8c5ce89d320be1.png"
			},
			{
				"txt": "설탕과 소금을 넣어줍니다.",
				"img": "https://recipe1.ezmember.co.kr/cache/recipe/2016/07/04/3c99d55ac68dfffcce95c42ccf2c7e6b1.png"
			},
			{
				"txt": "전분물(1:1비율)을 만들어 조금씩 넣어줍니다. 한번에 많이 넣으면 묵 되니까 조금씩 넣도록 합니다.",
				"img": "https://recipe1.ezmember.co.kr/cache/recipe/2016/07/04/7a8677ee5b5d26f3a0ff53fbb2df6bcc1.png"
			},
			{
				"txt": "적당한 농도가 되면 스탑!",
				"img": "https://recipe1.ezmember.co.kr/cache/recipe/2016/07/04/e5c79711f72ea1e1ad2f86219099e5401.png"
			},
			{
				"txt": "처음에 재워뒀던 녹말물의 위에 뜬 물을 따라 버려줍니다. ->된녹말 완성(튀김옷 재료)",
				"img": "https://recipe1.ezmember.co.kr/cache/recipe/2016/07/04/d7d76c7ca285054189f504eaa0106b8b1.png"
			},
			{
				"txt": "계란 흰자와 된녹말로 고기반죽을 해줍니다.",
				"img": "https://recipe1.ezmember.co.kr/cache/recipe/2016/07/04/2d7219f1a3b3d2c1ed6d10528fae0ee61.png"
			},
			{
				"txt": "된녹말을 넣어가며 농도를 맞춰줍니다.",
				"img": "https://recipe1.ezmember.co.kr/cache/recipe/2016/07/04/69ba4faef23eaf45b240306b86d99e411.png"
			},
			{
				"txt": "중약불에서 고기를 1차로 한번 튀겨줍니다. (작은 팬을 쓰면 기름 낭비를 줄일 수 있습니다)",
				"img": "https://recipe1.ezmember.co.kr/cache/recipe/2016/07/04/41b5512c089e37dd3063461e09e798651.png"
			},
			{
				"txt": "1차로 튀긴 고기를 건져낸 뒤,  2차로 중불에서 한번 더 바삭하게 튀겨줍니다.",
				"img": "https://recipe1.ezmember.co.kr/cache/recipe/2016/07/04/d7f51c3985ca45dcfe19e4bb23002a691.png"
			},
			{
				"txt": "노릇노릇해지면 모두 건져줍니다.",
				"img": "https://recipe1.ezmember.co.kr/cache/recipe/2016/07/04/0564cb4809f159de27aa6aa725b8787e1.png"
			},
			{
				"txt": "바삭 탕수육+야매 탕수육소스 완성!",
				"img": "https://recipe1.ezmember.co.kr/cache/recipe/2016/07/04/2ad809f5ab26c1f369d45247509cb7a31.png"
			}
		]
	},
	{
		"id": 27,
		"name": "[간단 자취요리] 포장마차 통순대 꼬치 만들기",
		"img": "https://recipe1.ezmember.co.kr/cache/recipe/2016/06/03/c8a3979a9c28a0a957722fc5df49c35f1.jpg",
		"summary": "오늘은 길가다가 자주 마주치는 포장마차에 요즘 자주 보이는통 순대 꼬치를 만들어 봤어요 :)썰어서 먹는거랑 또 다른 느낌의 통순대 꼬치인데요 !통순대는 마트진공포장 순대를 사셔도 되고 순대 파는곳에서 썰지말고 통으로 달라고 하셔도 돼요 :)+ 저 MBC 능력자들 촬영하게 되서 어제 사전녹화 했어요!!집에서 친구랑 요리하는 컨셉의 영상을 찍었어요지금껏 요리하면서 단 한번도 손벤적이 없었는데 ,한눈팔다가 어제 엄지손가락을... 베었어요 ㅠㅠ그래도 찍어놓은 영상이 몇개 있어서 어느정도 아물때 까지는영상 업로드는 문제 없을거에요 :)",
		"info": {
			"info1": "3인분",
			"info2": "30분 이내",
			"info3": "아무나"
		},
		"ingre": [
			{
				"ingre_name": "통순대",
				"ingre_count": "1",
				"ingre_unit": "봉지"
			},
			{
				"ingre_name": "고추장",
				"ingre_count": "1",
				"ingre_unit": "T"
			},
			{
				"ingre_name": "마늘",
				"ingre_count": "1",
				"ingre_unit": "T"
			},
			{
				"ingre_name": "간장",
				"ingre_count": "1/2",
				"ingre_unit": "T"
			},
			{
				"ingre_name": "케찹",
				"ingre_count": "1",
				"ingre_unit": "T"
			},
			{
				"ingre_name": "설탕",
				"ingre_count": "1",
				"ingre_unit": "T"
			},
			{
				"ingre_name": "올리고당",
				"ingre_count": "2",
				"ingre_unit": "T"
			}
		],
		"recipe": [
			{
				"txt": "재료를 준비해주세요.",
				"img": "https://recipe1.ezmember.co.kr/cache/recipe/2016/06/03/22b00e7011e03ed0f0968cc4c9446c961.jpg"
			},
			{
				"txt": "순대를 핫바 크기 만큼 잘라줍니다.",
				"img": "https://recipe1.ezmember.co.kr/cache/recipe/2016/06/03/6102c35b88d3ccbe1de89500b89979a31.jpg"
			},
			{
				"txt": "나무젓가락이나 꼬치를 순대에 끼워주세요.",
				"img": "https://recipe1.ezmember.co.kr/cache/recipe/2016/06/03/ec884793889b63f03f25359f26cde4571.jpg"
			},
			{
				"txt": "양념장 재료를 후라이팬에 넣고 졸여주세요.",
				"img": "https://recipe1.ezmember.co.kr/cache/recipe/2016/06/03/f12dc386ae0a28e3444e7acdb442394d1.jpg"
			},
			{
				"txt": "원하는 농도보다 살짝 묽을 때 불을 꺼줍니다.",
				"img": "https://recipe1.ezmember.co.kr/cache/recipe/2016/06/03/8add25ec18cae5d75638cd112e04ba821.jpg"
			},
			{
				"txt": "양념장을 순대에 발라주면 완성입니다.",
				"img": "https://recipe1.ezmember.co.kr/cache/recipe/2016/06/03/38a2e2b608e620ddac4b8f0ea101a2d81.jpg"
			}
		]
	},
	{
		"id": 28,
		"name": "[간단 자취요리] 남은순대 활용! 순대볶음 만들기",
		"img": "https://recipe1.ezmember.co.kr/cache/recipe/2016/05/27/64a8aa9b4e911b2890697acf3c700a981.jpg",
		"summary": "오늘은 비가 추적추적 내리는데요~ 다들 우산 챙겨나가셨나요?비내리는 날씨에도 어울리는 오늘의 메뉴는 순대볶음입니다!남아서 식은순대로도 맛있게 재탄생이 가능한 순대볶음!후다닥 만들어서 드셔보세요 !야채는 있는거 사용하시고 없으신건 생략하셔도 좋아요!대신 야채가 적거나, 없으면 물이 안나오기 때문에볶을때 살짝씩 물을 추가해주면서 볶아야 안타요!그리고 양념장은 제일 먼저 만들어두시고 냉장고에 잠시 숙성해주면 더 맛있어요 :)",
		"info": {
			"info1": "2인분",
			"info2": "30분 이내",
			"info3": "아무나"
		},
		"ingre": [
			{
				"ingre_name": "순대",
				"ingre_count": "1",
				"ingre_unit": "공기"
			},
			{
				"ingre_name": "양파",
				"ingre_count": "",
				"ingre_unit": ""
			},
			{
				"ingre_name": "당근",
				"ingre_count": "",
				"ingre_unit": ""
			},
			{
				"ingre_name": "깻잎",
				"ingre_count": "",
				"ingre_unit": ""
			},
			{
				"ingre_name": "들깨가루",
				"ingre_count": "",
				"ingre_unit": ""
			},
			{
				"ingre_name": "고춧가루",
				"ingre_count": "3",
				"ingre_unit": "T"
			},
			{
				"ingre_name": "고추장",
				"ingre_count": "3",
				"ingre_unit": "T"
			},
			{
				"ingre_name": "다진마늘",
				"ingre_count": "2",
				"ingre_unit": "T"
			},
			{
				"ingre_name": "간장",
				"ingre_count": "2",
				"ingre_unit": "T"
			},
			{
				"ingre_name": "설탕",
				"ingre_count": "2",
				"ingre_unit": "T"
			},
			{
				"ingre_name": "물",
				"ingre_count": "",
				"ingre_unit": ""
			}
		],
		"recipe": [
			{
				"txt": "재료를 준비합니다.",
				"img": "https://recipe1.ezmember.co.kr/cache/recipe/2016/05/27/b4f8a43c3bc36c905635b33216f768571.jpg"
			},
			{
				"txt": "준비한 양념을 섞어 양념장을 만들어 주세요.",
				"img": "https://recipe1.ezmember.co.kr/cache/recipe/2016/05/27/c0f33b9dce872a3e544e015193a1e67c1.jpg"
			},
			{
				"txt": "양파는 이렇게 썰어주세요.",
				"img": "https://recipe1.ezmember.co.kr/cache/recipe/2016/05/27/bad8d0944cdb5a3d3100f42956ecb0e71.jpg"
			},
			{
				"txt": "당근도 적당한 크기로 썰어주세요.",
				"img": "https://recipe1.ezmember.co.kr/cache/recipe/2016/05/27/33358277da481627ed09e08a36c6a90c1.jpg"
			},
			{
				"txt": "깻잎도 마찬가지 입니다.",
				"img": "https://recipe1.ezmember.co.kr/cache/recipe/2016/05/27/6e8ac46454109f0f3e9a2fd370bc83a71.jpg"
			},
			{
				"txt": "후라이팬에 기름을 두르고 양파와 당근을 볶아주세요.",
				"img": "https://recipe1.ezmember.co.kr/cache/recipe/2016/05/27/e1fe1882ec3bb3cbfc0cfa95ba751f1a1.jpg"
			},
			{
				"txt": "적당히 볶은 후 준비해둔 순대를 넣어주세요.",
				"img": "https://recipe1.ezmember.co.kr/cache/recipe/2016/05/27/86c1ba23f5bf09400da9d8548498b0aa1.jpg"
			},
			{
				"txt": "순대를 넣고 양념장도 넣어줍니다.",
				"img": "https://recipe1.ezmember.co.kr/cache/recipe/2016/05/27/e6f31c61e39e8cbf66e751617e3e578b1.jpg"
			},
			{
				"txt": "양념이 잘 배도록 볶은 후 들깨가루와 깻잎을 넣어 다시 한 번 볶아줍니다.",
				"img": "https://recipe1.ezmember.co.kr/cache/recipe/2016/05/27/a25e1c9d3f1f96253b797c04fa93febe1.jpg"
			}
		]
	},
	{
		"id": 29,
		"name": "[간단 자취요리] 저렴하게 칼질해보자! 두부 스테이크 만들기",
		"img": "https://recipe1.ezmember.co.kr/cache/recipe/2016/05/23/66a2be75f3be27e9c31e39e28cac30c01.jpg",
		"summary": "오늘은 두부스테이크 만들기입니다 :)재료도 얼마없고, 저렴하면서 고급진 메뉴이죠! 그리고 건강도 챙길 수 있고, 야채나 버섯을 안먹는 친구에게 먹이기도 아주 좋은 메뉴입니다 허허소스는 시판 돈가스소스,스테이크소스를 이용하면 됩니다!두부 물기제거를 귀찮으셔도 확실하게 해야 나중에 잘 안부서져요",
		"info": {
			"info1": "2인분",
			"info2": "60분 이내",
			"info3": "초급"
		},
		"ingre": [
			{
				"ingre_name": "두부",
				"ingre_count": "1",
				"ingre_unit": "모"
			},
			{
				"ingre_name": "양파",
				"ingre_count": "1",
				"ingre_unit": "개"
			},
			{
				"ingre_name": "당근",
				"ingre_count": "",
				"ingre_unit": ""
			},
			{
				"ingre_name": "양송이버섯",
				"ingre_count": "",
				"ingre_unit": ""
			},
			{
				"ingre_name": "계란",
				"ingre_count": "",
				"ingre_unit": ""
			},
			{
				"ingre_name": "부침가루",
				"ingre_count": "4",
				"ingre_unit": "T"
			},
			{
				"ingre_name": "소금",
				"ingre_count": "1",
				"ingre_unit": "t"
			},
			{
				"ingre_name": "후추",
				"ingre_count": "",
				"ingre_unit": ""
			}
		],
		"recipe": [
			{
				"txt": "재료를 준비합니다.",
				"img": "https://recipe1.ezmember.co.kr/cache/recipe/2016/05/23/8ecc1bc645c41c2994a7483cf34b209a1.jpg"
			},
			{
				"txt": "두부는 면보에 싸서 물기를 꼭 짜 줍니다.",
				"img": "https://recipe1.ezmember.co.kr/cache/recipe/2016/05/23/4ed8f601da450c27511a4b53a41c9faa1.jpg"
			},
			{
				"txt": "양파 반개는 얇게 채썰어 주세요.",
				"img": "https://recipe1.ezmember.co.kr/cache/recipe/2016/05/23/5aeb49ffc903763dc1e52e04de80e57d1.jpg"
			},
			{
				"txt": "또 다른 반개는 다져줍니다.",
				"img": "https://recipe1.ezmember.co.kr/cache/recipe/2016/05/23/a9737fc14e40e34cbc6687ba20f125a31.jpg"
			},
			{
				"txt": "버섯은 기둥을 제거해 줍니다.",
				"img": "https://recipe1.ezmember.co.kr/cache/recipe/2016/05/23/16e2145193d78e815decadebd9e07eb91.jpg"
			},
			{
				"txt": "그리고 잘게 다져줍니다.",
				"img": "https://recipe1.ezmember.co.kr/cache/recipe/2016/05/23/75a93bde59a78b404daef87a6c18885d1.jpg"
			},
			{
				"txt": "우깬 두부와 다진재료, 부침가루 계란 등을 같이 넣어줍니다.",
				"img": "https://recipe1.ezmember.co.kr/cache/recipe/2016/05/23/159d8c0ec3cd04bdec4c4d26f2df95191.jpg"
			},
			{
				"txt": "소금과 후추로 간을 해줍니다.",
				"img": "https://recipe1.ezmember.co.kr/cache/recipe/2016/05/23/474d2edab5a10374a3fbd822e22d74bf1.jpg"
			},
			{
				"txt": "적당하게 모양을 잡아 부서지지 않도록 합니다.",
				"img": "https://recipe1.ezmember.co.kr/cache/recipe/2016/05/23/79ea00c599d8d650db4c3e762d92a21a1.jpg"
			},
			{
				"txt": "후라이팬에 버터를 풀고 채썰어 둔 양파가 갈색으로 변할 때 까지 볶아줍니다.",
				"img": "https://recipe1.ezmember.co.kr/cache/recipe/2016/05/23/93d3b36698c7aaf25580f619505067951.jpg"
			},
			{
				"txt": "만들어둔 패티는 식용유에서 구워줍니다.",
				"img": "https://recipe1.ezmember.co.kr/cache/recipe/2016/05/23/0ee2589682439722dc2d7090631332631.jpg"
			},
			{
				"txt": "반대쪽도 잘 구워줍니다.",
				"img": "https://recipe1.ezmember.co.kr/cache/recipe/2016/05/23/c479a48719953bf56816c76bc1f556901.jpg"
			},
			{
				"txt": "만들어 놓은 패티와 양파 등을 통해 잘 플레이팅하고 두부패티에 맞는 아무 소스와 함께 곁들여 먹습니다.",
				"img": "https://recipe1.ezmember.co.kr/cache/recipe/2016/05/23/284f92ba9898518848461437ce9170451.jpg"
			}
		]
	},
	{
		"id": 30,
		"name": "[간단 자취요리] 남은 치킨의 대변신!! 깐풍기 만들기",
		"img": "https://recipe1.ezmember.co.kr/cache/recipe/2016/05/10/d80df0d4ee1acd4572f19849fa76f12e1.jpg",
		"summary": "안녕하세요~ 오늘은 남은 치킨 활용요리 깐풍기를 만들어봤어요자취하실때 치킨 시켜드시면 항상 몇조각이 남는데데워먹어도 물렁물렁하고...맛이없죠ㅠㅠ그래서 깐풍기를 만들어서 새로운 요리로 탄생시켜봤어요고추기름이 없으신분들은 기름에 고춧가루 넣고약불에서 끓여주시면 고추기름 완성!",
		"info": {
			"info1": "1인분",
			"info2": "30분 이내",
			"info3": "아무나"
		},
		"ingre": [
			{
				"ingre_name": "남은치킨",
				"ingre_count": "",
				"ingre_unit": ""
			},
			{
				"ingre_name": "고추",
				"ingre_count": "1~2개",
				"ingre_unit": "~개"
			},
			{
				"ingre_name": "파",
				"ingre_count": "",
				"ingre_unit": ""
			},
			{
				"ingre_name": "간장",
				"ingre_count": "2",
				"ingre_unit": "T"
			},
			{
				"ingre_name": "굴소스",
				"ingre_count": "2",
				"ingre_unit": "T"
			},
			{
				"ingre_name": "설탕",
				"ingre_count": "1",
				"ingre_unit": "T"
			},
			{
				"ingre_name": "다진마늘",
				"ingre_count": "1",
				"ingre_unit": "T"
			},
			{
				"ingre_name": "고추기름설탕",
				"ingre_count": "1",
				"ingre_unit": "T"
			},
			{
				"ingre_name": "식초",
				"ingre_count": "1",
				"ingre_unit": "T"
			},
			{
				"ingre_name": "후추",
				"ingre_count": "",
				"ingre_unit": "조금"
			}
		],
		"recipe": [
			{
				"txt": "재료들을 준비해주세요.",
				"img": "https://recipe1.ezmember.co.kr/cache/recipe/2016/05/10/e3259b7c27405abe82dea4bb199e683b1.jpg"
			},
			{
				"txt": "파는 적당하게 잘게 썰어주세요.",
				"img": "https://recipe1.ezmember.co.kr/cache/recipe/2016/05/10/4df81a33bf8345c79b0de35dd89a1a441.jpg"
			},
			{
				"txt": "고추는 씨를 빼주세요.",
				"img": "https://recipe1.ezmember.co.kr/cache/recipe/2016/05/10/844f2095660565d5dcabe87e2ffbf0e31.jpg"
			},
			{
				"txt": "씨를 뺀 후 채를 썬 후 잘게 썰어주세요.",
				"img": "https://recipe1.ezmember.co.kr/cache/recipe/2016/05/10/2a26b3b1e074302af95c82a7cd3b5aed1.jpg"
			},
			{
				"txt": "남은 치킨은 한 입 크기로 찢어줍니다.",
				"img": "https://recipe1.ezmember.co.kr/cache/recipe/2016/05/10/f4eedd6915d318df354be9acfb6e161d1.jpg"
			},
			{
				"txt": "달군 후라이팬에 고추기름을 두른 후 다진마늘을 넣고 볶아줍니다.",
				"img": "https://recipe1.ezmember.co.kr/cache/recipe/2016/05/10/12856a9e7d10373ee2f90723c474a6e51.jpg"
			},
			{
				"txt": "썰어 놓은 야채를 함께 넣고 볶아주세요.",
				"img": "https://recipe1.ezmember.co.kr/cache/recipe/2016/05/10/969955114a08f649fb87741a06caa01f1.jpg"
			},
			{
				"txt": "적당히 볶아지면 준비한 양념들을 넣고 물을 넣은 후 함께 볶아주세요.",
				"img": "https://recipe1.ezmember.co.kr/cache/recipe/2016/05/10/d67e127e99ced397ae0a8465490105a81.jpg"
			},
			{
				"txt": "소스가 졸면 치킨을 넣고 다시 함께 볶아주세요.",
				"img": "https://recipe1.ezmember.co.kr/cache/recipe/2016/05/10/46a50a103ee8ffca44c7f80c043c74ff1.jpg"
			},
			{
				"txt": "다 된 깐풍기는 그릇에 담아주면 완성입니다.",
				"img": "https://recipe1.ezmember.co.kr/cache/recipe/2016/05/10/4d264cac787b3bd62ed91e0e42774fd01.jpg"
			}
		]
	},
	{
		"id": 31,
		"name": "갈치조림 :: 간단한요리, 자취요리",
		"img": "https://recipe1.ezmember.co.kr/cache/recipe/2015/06/25/e6bfa336324a7c815ba9241a3b39c0411.jpg",
		"summary": "달달한 무와 감자를 곁들인 갈치조림짭쪼름한 국물에 하얀 생선살을 찍어먹는 게 별미입니다.",
		"info": {
			"info1": "2인분",
			"info2": "30분 이내",
			"info3": "초급"
		},
		"ingre": [
			{
				"ingre_name": "갈치",
				"ingre_count": "3",
				"ingre_unit": "토막"
			},
			{
				"ingre_name": "무(취향껏)",
				"ingre_count": "",
				"ingre_unit": ""
			},
			{
				"ingre_name": "감자(취향껏)",
				"ingre_count": "",
				"ingre_unit": ""
			},
			{
				"ingre_name": "고추장",
				"ingre_count": "1",
				"ingre_unit": "T"
			},
			{
				"ingre_name": "고춧가루",
				"ingre_count": "1",
				"ingre_unit": "T"
			},
			{
				"ingre_name": "간장",
				"ingre_count": "1",
				"ingre_unit": "T"
			},
			{
				"ingre_name": "매실액",
				"ingre_count": "1",
				"ingre_unit": "T"
			},
			{
				"ingre_name": "올리고당",
				"ingre_count": "1",
				"ingre_unit": "T"
			},
			{
				"ingre_name": "다진마늘",
				"ingre_count": "1",
				"ingre_unit": "t"
			},
			{
				"ingre_name": "참기름",
				"ingre_count": "1",
				"ingre_unit": "t"
			}
		],
		"recipe": [
			{
				"txt": "양념 재료를 분량대로 준비해서 섞어준다. 고춧가루를 다 써서 생략함 매실액과 올리고당은 설탕으로 대체 가능하고 간장, 고추장, 마늘은 꼭 넣기 마늘은 최대한 잘게 다져서 덩어리가 없게 하는 것이 좋다.",
				"img": "https://recipe1.ezmember.co.kr/cache/recipe/2015/06/25/7e5b98816b791a1acee2cf77c225c18a1.jpg"
			},
			{
				"txt": "무와 감자를 썰어서 무를 먼저 깔고 그 위에 감자를 올린다. 이대로 익히면 무조림, 감자조림 완성! 빨리 익히고 싶으면 깍둑썰기 하고, 바스러지는 게 싫으면 큼직하게 썰면 됨",
				"img": "https://recipe1.ezmember.co.kr/cache/recipe/2015/06/25/40302e493626333524acef098736b16f1.jpg"
			},
			{
				"txt": "위에 갈치를 올리고 양념장을 얹어준다. 갈치 올리면 갈치조림, 고등어 올리면 고등어조림, 꽁치 올리면 꽁치조림 마트에 캔으로 된 생선 많이 파니까 그거 사다가 살짝 헹궈서 올려도 되고 생물로 올려도 상관없다. 캔 제품은 이미 간이 많이 되어있으니까 양념을 조절해가며 넣는다.",
				"img": "https://recipe1.ezmember.co.kr/cache/recipe/2015/06/25/c49932afcee3880142e35acc1a0f86bf1.jpg"
			},
			{
				"txt": "뚜껑을 닫고 센 불로 가열해서 보글보글 끓어오르면b약불로 줄이고 익힌다. 10분 정도면 다 익고, 찔러봐서 푹 들어가지 않고 덜 익었으면 좀 더 익히기 생선은 금방 익음! 무나 감자를 크게 썰었으면 익는데 좀 더 오래걸린다.",
				"img": "https://recipe1.ezmember.co.kr/cache/recipe/2015/06/25/c763dccf3f761ea1d28b1318e7635e991.jpg"
			},
			{
				"txt": "다 익기만 하면 갈치조림 끝 실파 송송 썰어서 올려주면 색감이 더 예쁘다",
				"img": "https://recipe1.ezmember.co.kr/cache/recipe/2015/06/25/4fcce3e0453d6c3207d57c3670c341211.jpg"
			}
		]
	}
]